Workbook

Sheet Cover
C4: NAV Model
C5: Net Asset Value Model - Range Resources Corp. (NYSE:RRC)
C7: Theo Pham
C8: Laszlo MacCallum-von Hahn
C17: Public and Non-Confidential
C21: Last Updated | F21: 45994
C23: Company Inputs
C24: Company Name | F24: Range Resources Corperation
C25: Ticker | F25: NYSE: RRC
C26: Pricing Date | F26: =F21 -> 45994
C27: Currency | F27: USD
C31: Legend
C32: Black = Text / Intraworksheet Formulas
C33: Blue = Inputs
C34: Green = Links Between Worksheets

Sheet Inputs & Assumptions
D2: =Cover!C5 -> Net Asset Value Model - Range Resources Corp. (NYSE:RRC)
D3: Inputs & Assumptions
D5: Currently Running Commodity Price case: | H5: {=_xlfn.IFS(L37 = 1,"Street", L37=2,"Bear",L37=3,"Base",L37=4,"Bull")} -> Street
B8: 1. | C8: Inputs & Assumptions
C10: a. | D10: Investment Timeline
D12: Valuation Date
D13: Valuation Date | G13: =Cover!F21 -> 45994
C16: a. | D16: Company Inputs
H19: Units
D21: Company Name | H21: Name | K21: =Cover!F24 -> Range Resources Corperation
D22: Ticker Symbol | H22: BBG | L22: RRC US
D24: Current Share price | H24: $ | L24: 39.89
D25: FD Shares Outstanding | H25: mm | L25: 239.03
D26: Market Cap. | H26: mm $ | L26: =L24*L25 -> 9534.9067
D28: Historical Beta | H28: 5y | L28: =Comps!T3 -> 0.98369845
D30: Credit Profile
D31: Pre-tax cost of debt (Kd) | H31: % | L31: 0.0547
V32: =NAV!N36 -> 0.24943221
D33: Other
D34: Effective Tax Rate | H34: % | L34: =NAV!AU29 -> 0.25
D35: Bbl to Mcfe converstion | L35: 6
D36: Estimated realised NGL premium | L36: 1.63
D37: Commodity Price case | L37: =NAV!AU28 -> 1
D40: Discount Rate (WACC) | H40: % | L40: ='Cost of Capital'!G81 -> 0.083972982
C44: c. | D44: Market Data | J44: sources
D46: Required Returns | F46: units
D47: Risk-Free Rate of Return (Rf) | F47: % | G47: 0.04 | J47: fred: 2025.11.25
F48: x
D49: Equity Risk Premium (Rm-Rf) | F49: % | G49: 0.0576 | J49: Aswath Damodaran, U.S. ERP (TTM) as of November 1 2025
C52: d. | D52: Production and Drilling assumptions
D55: Proportion of production | H55: Units
D57: Share of production
E58: Natural Gas | H58: % | L58: 0.685
E59: Natural Gas Liguids (NGL) | H59: % | L59: 0.2986
E60: Oil | H60: % | L60: 0.0164
D63: Proved Developped Reserves | H63: Units
D65: Net PD Reserves | H65: Mmcfe | L65: 11930793
D66: PDP Daily production (Current) | H66: Mmcfe/d | L66: 2227.8
D67: Proved production decline rate | H67: % | L67: 0.05
D68: Estimated Reserve Life
D71: Production Expense Assumptions
D73: Production taxes | H73: $/Mcfe | L73: 0.04
D74: Lease OpEx | H74: $/Mcfe | L74: 0.14
D75: Trabsportation | H75: $/Mcfe | L75: 1.642
D77: Future Maintainance CapEx % D&C CapEx | H77: % | L77: 0.2
D78: Future Maintaincnce CapEx | H78: $MM | L78: ='PUD Reserves'!AP24*'Inputs & Assumptions'!L77 -> 847.42668
D80: Net PP&E Balance to Depreciate/Deplete: | L80: 6424.2
D81: Proved Undevelopped Reserves | H81: Units
D84: Total Proven Undevelopped Reserves (net) | H84: Mmcffe | L84: 6200683
D85: Average EUR per well | H85: Mmcffe | L85: =NAV!AU14 -> 15000
D86: Potential net future locations | H86: # | L86: =L84/L85 -> 413.37887
D88: Net new wells drilled per year | L88: {=_xlfn.IFS(OR(L37=1,L37=3), 55, L37 = 2, 60, L37 = 4, 50)} -> 55
D89: First year production % EUR | H89: % | L89: =NAV!AU15 -> 0.125
D90: Initial production | H90: Mmcfe/d | L90: =L85*L89/365 -> 5.1369863
D92: Initial D&C costs per well | H92: $MM | L92: 10.25
D93: Future D&C CapEx | H93: $MM | L93: ='PUD Reserves'!AP24 -> 4237.1334
D96: NAV Assumptions | H96: Units
E98: G&A expense % of Revenue | L98: 0.074

Sheet Cost of Capital
C2: =Cover!C5 -> Net Asset Value Model - Range Resources Corp. (NYSE:RRC)
C3: Commodity Price Assumptions
C5: Currently Running Commodity Price case: | G5: {=_xlfn.IFS('Inputs & Assumptions'!L37= 1,"Street", 'Inputs & Assumptions'!L37=2,"Bear",'Inputs & Assumptions'!L37=3,"Base",'Inputs & Assumptions'!L37=4,"Bull")} -> Street
B8: x | C8: 1. | D8: Energy Transfer Cost of Capital
C10: x | D10: a. Key Assumptions
D12: WACC Inputs | G12: units
D14: Equity:
D15: Risk-Free Rate of Return (Rf) | G15: % | H15: 0.04
G16: x
D17: Equity Risk Premium (Rm-Rf) | G17: % | H17: 0.0576
D19: Debt:
D20: Pretax Cost of Debt (Kd) | G20: % | H20: 0.0547
D22: Market Capitalization | G22: mm dollars | H22: 9326.9506
D24: Net Debt | G24: th dollars | H24: 1393.4
D26: Effective Tax rate | G26: % | H26: 0.25
D28: Company
D29: Historical Beta | G29: x | H29: 0.88
C32: x | D32: b. Beta Calculation
D36: Comps Beta
D37: Name | E37: Ticker | F37: 5 Year Beta | G37: Debt | H37: % Debt | I37: Equity Value | J37: % Equity | K37: Tax Rate | L37: Unlevered Beta
D38: APA CORP | E38: APA US | F38: 1.1581892 | G38: 4219.0001 | H38: 0.32372837 | I38: 8813.5309 | J38: 0.67627163 | K38: 0.25 | L38: 0.85222267
D39: COMSTOCK RESOURCES INC | E39: CRK US | F39: 1.1035831 | G39: 3183.927 | H39: 0.29571931 | I39: 7582.7931 | J39: 0.70428069 | K39: 0.25 | L39: 0.83928007
D40: PERMIAN RESOURCES CORP | E40: PR US | F40: 1.1599289 | G40: 3577.2119 | H40: 0.23068878 | I40: 11929.446 | J40: 0.76931122 | K40: 0.25 | L40: 0.9469596
D41: CNX RESOURCES CORP | E41: CNX US | F41: 0.80980969 | G41: 2773.748 | H41: 0.3495524 | I41: 5161.3941 | J41: 0.6504476 | K41: 0.25 | L41: 0.57717719
D42: COTERRA ENERGY INC | E42: CTRA US | F42: 0.78887898 | G42: 4019.0001 | H42: 0.16665588 | I42: 20096.56 | J42: 0.83334412 | K42: 0.25 | L42: 0.68598866
D43: DEVON ENERGY CORP | E43: DVN US | F43: 1.0494801 | G43: 7271.0001 | H43: 0.24092117 | I43: 22908.996 | J43: 0.75907883 | K43: 0.25 | L43: 0.84769505
D44: EXPAND ENERGY CORP | E44: EXE US | F44: 0.83211299 | G44: 4522.9998 | H44: 0.13742859 | I44: 28388.637 | J44: 0.86257141 | K44: 0.25 | L44: 0.74329435
D45: EQT CORP | E45: EQT US | F45: 0.93071324 | G45: 7982.0861 | H45: 0.17824489 | I45: 36799.484 | J45: 0.82175511 | K45: 0.25 | L45: 0.80048913
D46: DIAMONDBACK ENERGY INC | E46: FANG US | F46: 0.97279572 | G46: 16083 | H46: 0.27290357 | I46: 42849.906 | J46: 0.72709643 | K46: 0.25 | L46: 0.75910705
D47: CONOCOPHILLIPS | E47: COP US | F47: 0.84169963 | G47: 17226 | H47: 0.13782938 | I47: 107754.61 | J47: 0.86217062 | K47: 0.25 | L47: 0.75158636
D49: Median: | F49: 0.95175448 | G49: 4370.9999 | H49: 0.23580497 | I49: 21502.778 | J49: 0.76419503 | K49: 0.25 | L49: 0.77979809
D51: Range Unlevered Beta | E51: RRC US | F51: 0.98369845 | G51: 1372.913 | H51: 0.13055138 | I51: 9143.353 | J51: 0.86944862 | K51: 0.25 | L51: 0.8841314
D54: Range - Relevered Beta
D55: Calculated Using: | E55: Ticker | F55: Unlevered Beta (Comps) | G55: Debt | H55: % Debt | I55: Equity Value | J55: % Equity | K55: Tax Rate | L55: Levered Beta
D56: Range Unlevered Beta | E56: RRC US | F56: 0.77979809 | G56: 1372.913 | H56: 0.13055138 | I56: 9143.353 | J56: 0.86944862 | K56: 0.25 | L56: 0.86761557
D57: "Optimal" Capital Structure: | F57: 0.77979809 | G57: 2479.7879 | H57: 0.23580497 | I57: 8036.4782 | J57: 0.76419503 | K57: 0.25 | L57: 0.96026276
C59: x | D59: c. Detailed WACC Calculation
D62: At Historical | I62: At Current Capital Structure | N62: At Optimal Capital Structure
D63: Equity | I63: Equity | N63: Equity
D64: Equity Risk | G64: 0.0576 | I64: Equity Risk | L64: 0.0576 | N64: Equity Risk | Q64: 0.0576
D65: Beta | G65: 0.88 | I65: Beta | L65: 0.86761557 | N65: Beta | Q65: 0.96026276
D66: Adjusted Equity Risk Premium | G66: 0.050688 | I66: Adjusted Equity Risk Premium | L66: 0.049974657 | N66: Adjusted Equity Risk Premium | Q66: 0.055311135
D67: Add: Risk-free Rate of Return (Rf) | G67: 0.04 | I67: Add: Risk-free Rate of Return (Rf) | L67: 0.04 | N67: Add: Risk-free Rate of Return (Rf) | Q67: 0.04
D68: Cost of Equity (Ke) | G68: 0.090688 | I68: Cost of Equity (Ke) | L68: 0.089974657 | N68: Cost of Equity (Ke) | Q68: 0.095311135
D69: Multiply by: E / (D+E) | G69: 0.86944862 | I69: Multiply by: E / (D+E) | L69: 0.86944862 | N69: Multiply by: E / (D+E) | Q69: 0.76419503
D70: Cost of Equity Portion | G70: 0.078848557 | I70: Cost of Equity Portion | L70: 0.078228342 | N70: Cost of Equity Portion | Q70: 0.072836295
D72: Debt | I72: Debt | N72: Debt
D73: Cost of Debt (Kd) | G73: 0.0547 | I73: Cost of Debt (Kd) | L73: 0.0547 | N73: Cost of Debt (Kd) | Q73: 0.0547
D74: Assumed Tax Rate | G74: 0.25 | I74: Assumed Tax Rate | L74: 0.25 | N74: Assumed Tax Rate | Q74: 0.25
D75: After-Tax Cost of Debt | G75: 0.041025 | I75: After-Tax Cost of Debt | L75: 0.041025 | N75: After-Tax Cost of Debt | Q75: 0.041025
D76: Multiply by: D / (D+E) | G76: 0.13055138 | I76: Multiply by: D / (D+E) | L76: 0.13055138 | N76: Multiply by: D / (D+E) | Q76: 0.23580497
D77: Cost of Debt Portion | G77: 0.0053558703 | I77: Cost of Debt Portion | L77: 0.0053558703 | N77: Cost of Debt Portion | Q77: 0.0096738991
D79: WACC | G79: 0.084204427 | I79: WACC | L79: 0.083584212 | N79: WACC | Q79: 0.082510194
D81: Average WACC Produced by All Methods: | G81: =NAV!AU40 -> 0.083972982

Sheet Comps
A1: Name | B1: Ticker | C1: Price:D-1 | D1: Mkt Cap (USD) | E1: Net Debt LF | F1: BEst EV | G1: EV/BE Sales Curr Yr | H1: EV/Next Yr Est Sales | I1: BEst Curr EV/BEst EBITDA:1FY | J1: BEst Curr EV/BEst EBITDA:1BF | K1: BEst P/E:1BF | L1: BEst P/E:1FY | M1: Net Debt to EBITDA LF | N1: BEst EBITDA:2024 | O1: BEst EBITDA:1FY | P1: BEst EBITDA:1BF | Q1: BEst NI:2024 | R1: BEst NI:1FY | S1: BEst NI:1BF | T1: Beta:Y-5 | V1: Leverage
A2: Median | B2: 0 | C2: 37.419998 | D2: 20096.56 | E2: 4219.0001 | F2: 23555.338 | G2: 3.2102293 | H2: 3.0315848 | I2: 6.3968049 | J2: 5.3704974 | K2: 12.687823 | L2: 13.43663 | M2: 1.074857 | N2: 3457.2001 | O2: 4911.1111 | P2: 5167.8376 | Q2: 1177.43 | R2: 1370.48 | S2: 1934.2434 | T2: 0.97279572 | V2: =E2/(E2+D2) -> 0.17351029
A3: RANGE RESOURCES CORP | B3: RRC US | C3: 37.799999 | D3: 9143.353 | E3: 1372.913 | F3: 10304.535 | G3: 3.5189112 | H3: 3.1327547 | I3: 7.4439277 | J3: 6.4139877 | K3: 10.717072 | L3: 13.43663 | M3: 1.2075059 | N3: 1184.7 | O3: 1391.7308 | P3: 1615.1849 | Q3: 535.58301 | R3: 688.174 | S3: 851.41547 | T3: 0.98369845 | V3: =E3/(E3+D3) -> 0.13055138
A4: APA CORP | B4: APA US | C4: 24.08 | D4: 8813.5309 | E4: 4219.0001 | F4: 13605.174 | G4: 1.6395862 | H4: 1.8072388 | I4: 2.6529707 | J4: 2.920124 | K4: 8.3853064 | L4: 6.9374651 | M4: 0.78771502 | N4: 5522.8001 | O4: 5173.2692 | P4: 4700.0374 | Q4: 1398.27 | R4: 1292.071 | S4: 995.61793 | T4: 1.1581892 | V4: =E4/(E4+D4) -> 0.32372837
A5: COMSTOCK RESOURCES INC | B5: CRK US | C5: 25.139999 | D5: 7582.7931 | E5: 3183.927 | F5: 10689.339 | G5: 5.7971591 | H5: 4.9395569 | I5: 9.9944429 | J5: 8.1798603 | K5: 28.06714 | L5: 50.23301 | M5: 3.2204919 | N5: 850.56301 | O5: 1095.1765 | P5: 1338.2756 | Q5: -112.381 | R5: 153.133 | S5: 279.59193 | T5: 1.1035831 | V5: =E5/(E5+D5) -> 0.29571931
A6: PERMIAN RESOURCES CORP | B6: PR US | C6: 14.11 | D6: 11929.446 | E6: 3577.2119 | F6: 16346.771 | G6: 2.9406542 | H6: 2.8874576 | I6: 3.9705116 | J6: 4.0490057 | K6: 11.787467 | L6: 11.31786 | M6: 0.98033798 | N6: 3684.8901 | O6: 3869.1429 | P6: 3794.1448 | Q6: 1177.43 | R6: 1045.591 | S6: 973.33612 | T6: 1.1599289 | V6: =E6/(E6+D6) -> 0.23068878
A7: CNX RESOURCES CORP | B7: CNX US | C7: 37.419998 | D7: 5161.3941 | E7: 2773.748 | F7: 7760.283 | G7: 3.9256161 | H7: 3.9112915 | I7: 6.3968049 | J7: 6.1403669 | K7: 15.209184 | L7: 17.439636 | M7: 2.794297 | N7: 996.81798 | O7: 1213.8125 | P7: 1264.4991 | Q7: 236 | R7: 361.5 | S7: 393.34101 | T7: 0.80980969 | V7: =E7/(E7+D7) -> 0.3495524
A8: COTERRA ENERGY INC | B8: CTRA US | C8: 25.84 | D8: 20096.56 | E8: 4019.0001 | F8: 23555.338 | G8: 3.2102293 | H8: 3.0315848 | I8: 5.0298763 | J8: 4.6302422 | K8: 10.244236 | L8: 11.674038 | M8: 0.91403198 | N8: 3406.4399 | O8: 4757.2857 | P8: 5167.8376 | Q8: 1200.15 | R8: 1705.261 | S8: 1934.2434 | T8: 0.78887898 | V8: =E8/(E8+D8) -> 0.16665588
A9: DEVON ENERGY CORP | B9: DVN US | C9: 35.82 | D9: 22908.996 | E9: 7271.0001 | F9: 29793.746 | G9: 1.9584351 | H9: 2.0764168 | I9: 4.0523317 | J9: 4.1338427 | K9: 8.9505181 | L9: 9.0508055 | M9: 0.936261 | N9: 7538.5201 | O9: 7447.5625 | P9: 7300.7295 | Q9: 2961.5401 | R9: 2558.7 | S9: 2506.8279 | T9: 1.0494801 | V9: =E9/(E9+D9) -> 0.24092117
A10: EXPAND ENERGY CORP | B10: EXE US | C10: 116.01 | D10: 28388.637 | E10: 4522.9998 | F10: 32503.406 | G10: 2.8689381 | H10: 2.7397825 | I10: 6.6758086 | J10: 5.3704974 | K10: 12.687823 | L10: 20.022678 | M10: 1.074857 | N10: 2095.9601 | O10: 4911.1111 | P10: 6104.629 | Q10: 207.28701 | R10: 1370.48 | S10: 2231.9713 | T10: 0.83211299 | V10: =E10/(E10+D10) -> 0.13742859
A11: EQT CORP | B11: EQT US | C11: 56.759998 | D11: 36799.484 | E11: 7982.0861 | F11: 48078.365 | G11: 5.8055244 | H11: 5.0631977 | I11: 8.9587366 | J11: 7.2329186 | K11: 13.360011 | L11: 20.263643 | M11: 1.433593 | N11: 3457.2001 | O11: 5404.8077 | P11: 6694.278 | Q11: 679.43501 | R11: 1832.87 | S11: 2705.9081 | T11: 0.93071324 | V11: =E11/(E11+D11) -> 0.17824489
A12: DIAMONDBACK ENERGY INC | B12: FANG US | C12: 147.02 | D12: 42849.906 | E12: 16083 | F12: 63622.073 | G12: 4.4680884 | H12: 4.6305387 | I12: 6.5048021 | J12: 6.6696185 | K12: 12.712326 | L12: 11.510044 | M12: 1.552713 | N12: 7363.4002 | O12: 10066.241 | P12: 9817.5177 | Q12: 3303.6301 | R12: 3793.185 | S12: 3339.102 | T12: 0.97279572 | V12: =E12/(E12+D12) -> 0.27290357
A13: CONOCOPHILLIPS | B13: COP US | C13: 86.620003 | D13: 107754.61 | E13: 17226 | F13: 124785.18 | G13: 2.0860243 | H13: 2.2769625 | I13: 4.9012484 | J13: 5.1277621 | K13: 13.842911 | L13: 13.454714 | M13: 0.717152 | N13: 24906.199 | O13: 25499.75 | P13: 24373.455 | Q13: 9220.2895 | R13: 8152.643 | S13: 7437.4093 | T13: 0.84169963 | V13: =E13/(E13+D13) -> 0.13782938
J15: =AVERAGE(J3:J13) -> 5.5334751

Sheet Commodity Price Assumptions
G2: =Cover!C5 -> Net Asset Value Model - Range Resources Corp. (NYSE:RRC)
G3: Commodity Price Assumptions | O3: 2025 | P3: 2026 | Q3: =P3+1 -> 2027 | R3: =Q3+1 -> 2028 | S3: =R3+1 -> 2029
G5: Currently Running Commodity Price case: | K5: {=_xlfn.IFS('Inputs & Assumptions'!L37= 1,"Street", 'Inputs & Assumptions'!L37=2,"Bear",'Inputs & Assumptions'!L37=3,"Base",'Inputs & Assumptions'!L37=4,"Bull")} -> Street
B8: 1. | C8: Natural Gas Price Assumptions
F10: Natural Gas prices | H10: ='Inputs & Assumptions'!L37 -> 1 | I10: {=_xlfn.IFS(H10= 1,"Street", H10=2,"Bear",H10=3,"Base",H10=4,"Bull")} -> Street | O10: =OFFSET(O12,$H10,0) -> 3.5 | P10: =OFFSET(P12,$H10,0) -> 3.84 | Q10: =OFFSET(Q12,$H10,0) -> 3.85 | R10: =OFFSET(R12,$H10,0) -> 3.81 | S10: =OFFSET(S12,$H10,0) -> 3.84
H12: unit
F13: Street | H13: $/Mcfe | O13: =O15 -> 3.5 | P13: =P15 -> 3.84 | Q13: =Q15 -> 3.85 | R13: =R15 -> 3.81 | S13: =S15 -> 3.84
F14: Bear | H14: $/Mcfe | O14: =O15-U14 -> 2.67 | P14: =P15-V14 -> 2.67 | Q14: =Q15-W14 -> 2.67 | R14: =R15-X14 -> 2.7 | S14: =S15-Y14 -> 2.75 | U14: 0.83 | V14: 1.17 | W14: 1.18 | X14: 1.11 | Y14: 1.09
F15: Base | H15: $/Mcfe | O15: =3.5 -> 3.5 | P15: =O15+0.34 -> 3.84 | Q15: =P15+0.01 -> 3.85 | R15: =Q15-0.04 -> 3.81 | S15: =NAV!AU39 -> 3.84
F16: Bull | H16: $/Mcfe | O16: =O15+0.2 -> 3.7 | P16: =P15+0.02 -> 3.86 | Q16: =Q15+0.22 -> 4.07 | R16: =R15+0.34 -> 4.15 | S16: =S15+0.56 -> 4.4
B20: 2. | C20: Oil Price Assumprions
F23: Oil Prices | H23: ='Inputs & Assumptions'!L37 -> 1 | I23: {=_xlfn.IFS(H23= 1,"Street", H23=2,"Bear",H23=3,"Base",H23=4,"Bull")} -> Street | O23: =OFFSET(O25,$H23,0) -> 64.7428 | P23: =OFFSET(P25,$H23,0) -> 58.7556 | Q23: =OFFSET(Q25,$H23,0) -> 63.66 | R23: =OFFSET(R25,$H23,0) -> 67.5392 | S23: =OFFSET(S25,$H23,0) -> 69.1789
H25: unit
F26: Street | H26: $/Bbl | O26: =O28 -> 64.7428 | P26: =P28 -> 58.7556 | Q26: =Q28 -> 63.66 | R26: =R28 -> 67.5392 | S26: =S28 -> 69.1789
F27: Bear | H27: $/Bbl | O27: =O28+W27 -> 63.89 | P27: =P28+X27 -> 54.0056 | Q27: =Q28+Y27 -> 58.91 | R27: =R28+Z27 -> 62.45 | S27: =S28+AA27 -> 66.122 | W27: -0.8528 | X27: -4.75 | Y27: -4.75 | Z27: -5.0892 | AA27: -3.0569
F28: Base | H28: $/Bbl | O28: 64.7428 | P28: =O28+X28 -> 58.7556 | Q28: =P28+Y28 -> 63.66 | R28: =Q28+Z28 -> 67.5392 | S28: =R28+AA28 -> 69.1789 | X28: -5.9872 | Y28: 4.9044 | Z28: 3.8792 | AA28: 1.6397
F29: Bull | H29: $/Bbl | O29: =O28+W29 -> 67.862 | P29: =P28+X29 -> 63.7 | Q29: =Q28+Y29 -> 67.67 | R29: =R28+Z29 -> 72.702 | S29: =S28+AA29 -> 71.422 | W29: 3.1192 | X29: 4.9444 | Y29: 4.01 | Z29: 5.1628 | AA29: 2.2431
B33: 3. | C33: NGL Price assumptions
C35: a. | D35: Natural Gasoline Price forecast
F38: Nat. Gasoline Prices | H38: ='Inputs & Assumptions'!L37 -> 1 | I38: {=_xlfn.IFS(H38= 1,"Street", H38=2,"Bear",H38=3,"Base",H38=4,"Bull")} -> Street | K38: Weight: | L38: 0.08 | O38: =OFFSET(O40,$H38,0) -> 650.5433 | P38: =OFFSET(P40,$H38,0) -> 623.1 | Q38: =OFFSET(Q40,$H38,0) -> 643.96 | R38: =OFFSET(R40,$H38,0) -> 661.19 | S38: =OFFSET(S40,$H38,0) -> 679.35
H40: unit
F41: Street | H41: $/metric Tonne | O41: =O43 -> 650.5433 | P41: =P43 -> 623.1 | Q41: =Q43 -> 643.96 | R41: =R43 -> 661.19 | S41: =S43 -> 679.35
F42: Bear | H42: $/metric Tonne | O42: =O43-20 -> 630.5433 | P42: =P43-20 -> 603.1 | Q42: =Q43-20 -> 623.96 | R42: =R43-20 -> 641.19 | S42: =S43-20 -> 659.35
F43: Base | H43: $/metric Tonne | O43: 650.5433 | P43: 623.1 | Q43: 643.96 | R43: 661.19 | S43: 679.35
F44: Bull | H44: $/metric Tonne | O44: =O43+20 -> 670.5433 | P44: =P43+20 -> 643.1 | Q44: =Q43+20 -> 663.96 | R44: =R43+20 -> 681.19 | S44: =S43+20 -> 699.35
F47: Nat. Gasoline Prices | H47: ='Inputs & Assumptions'!L37 -> 1 | I47: {=_xlfn.IFS(H47= 1,"Street", H47=2,"Bear",H47=3,"Base",H47=4,"Bull")} -> Street | O47: =OFFSET(O49,$H47,0) -> 56.081319 | P47: =OFFSET(P49,$H47,0) -> 53.715517 | Q47: =OFFSET(Q49,$H47,0) -> 55.513793 | R47: =OFFSET(R49,$H47,0) -> 56.999138 | S47: =OFFSET(S49,$H47,0) -> 58.564655
H49: unit
F50: Street | H50: $/Bbl | O50: =O52 -> 56.081319 | P50: =P52 -> 53.715517 | Q50: =Q52 -> 55.513793 | R50: =R52 -> 56.999138 | S50: =S52 -> 58.564655
F51: Bear | H51: $/Bbl | O51: =O52-2 -> 54.081319 | P51: =P52-2 -> 51.715517 | Q51: =Q52-2 -> 53.513793 | R51: =R52-2 -> 54.999138 | S51: =S52-2 -> 56.564655
F52: Base | H52: $/Bbl | O52: =O43/11.6*(1+NAV!AU49) -> 56.081319 | P52: =O52+U52 -> 53.715517 | Q52: =P52+V52 -> 55.513793 | R52: =Q52+W52 -> 56.999138 | S52: =R52+X52 -> 58.564655 | U52: -2.3658017 | V52: 1.7982759 | W52: 1.4853448 | X52: 1.5655172
F53: Bull | H53: $/Bbl | O53: =O52+2 -> 58.081319 | P53: =P52+2 -> 55.715517 | Q53: =Q52+2 -> 57.513793 | R53: =R52+2 -> 58.999138 | S53: =S52+2 -> 60.564655
C56: b. | D56: Propane Price forecast
F59: Propane Price Forecast | H59: ='Inputs & Assumptions'!L37 -> 1 | I59: {=_xlfn.IFS(H59= 1,"Street", H59=2,"Bear",H59=3,"Base",H59=4,"Bull")} -> Street | K59: Weight: | L59: 0.15 | O59: =OFFSET(O61,$H59,0) -> 0.61542 | P59: =OFFSET(P61,$H59,0) -> 0.62001667 | Q59: =OFFSET(Q61,$H59,0) -> 0.6146525 | R59: =OFFSET(R61,$H59,0) -> 0.62072917 | S59: =OFFSET(S61,$H59,0) -> 0.60604167
H61: unit
F62: Street | H62: $/Gal | O62: =O64 -> 0.61542 | P62: =P64 -> 0.62001667 | Q62: =Q64 -> 0.6146525 | R62: =R64 -> 0.62072917 | S62: =S64 -> 0.60604167
F63: Bear | H63: $/Gal | O63: =O64-0.03 -> 0.58542 | P63: =P64-0.03 -> 0.59001667 | Q63: =Q64-0.03 -> 0.5846525 | R63: =R64-0.03 -> 0.59072917 | S63: =S64-0.03 -> 0.57604167
F64: Base | H64: $/Gal | O64: 0.61542 | P64: 0.62001667 | Q64: 0.6146525 | R64: 0.62072917 | S64: 0.60604167
F65: Bull | H65: $/Gal | O65: =O64+0.03 -> 0.64542 | P65: =P64+0.03 -> 0.65001667 | Q65: =Q64+0.03 -> 0.6446525 | R65: =R64+0.03 -> 0.65072917 | S65: =S64+0.03 -> 0.63604167
F68: Propane Price Forecast | H68: ='Inputs & Assumptions'!L37 -> 1 | I68: {=_xlfn.IFS(H68= 1,"Street", H68=2,"Bear",H68=3,"Base",H68=4,"Bull")} -> Street | O68: =OFFSET(O70,$H68,0) -> 25.84764 | P68: =OFFSET(P70,$H68,0) -> 26.0407 | Q68: =OFFSET(Q70,$H68,0) -> 25.815405 | R68: =OFFSET(R70,$H68,0) -> 26.070625 | S68: =OFFSET(S70,$H68,0) -> 25.45375
H70: unit
F71: Street | H71: $/Bbl | O71: =O73 -> 25.84764 | P71: =P73 -> 26.0407 | Q71: =Q73 -> 25.815405 | R71: =R73 -> 26.070625 | S71: =S73 -> 25.45375
F72: Bear | H72: $/Bbl | O72: =O73-0.03 -> 25.81764 | P72: =P73-0.03 -> 26.0107 | Q72: =Q73-0.03 -> 25.785405 | R72: =R73-0.03 -> 26.040625 | S72: =S73-0.03 -> 25.42375
F73: Base | H73: $/Bbl | O73: =O64*42*(1+NAV!AU49) -> 25.84764 | P73: =O73+U73 -> 26.0407 | Q73: =P73+V73 -> 25.815405 | R73: =Q73+W73 -> 26.070625 | S73: =R73+X73 -> 25.45375 | U73: 0.19306 | V73: -0.225295 | W73: 0.25522 | X73: -0.616875
F74: Bull | H74: $/Bbl | O74: =O73+0.03 -> 25.87764 | P74: =P73+0.03 -> 26.0707 | Q74: =Q73+0.03 -> 25.845405 | R74: =R73+0.03 -> 26.100625 | S74: =S73+0.03 -> 25.48375
C77: c. | D77: Ethane price Forecast
F80: Ethane Price Forecast | H80: 4 | I80: {=_xlfn.IFS(H80= 1,"Street", H80=2,"Bear",H80=3,"Base",H80=4,"Bull")} -> Bull | K80: Weight: | L80: 0.57 | O80: =OFFSET(O82,$H80,0) -> 0.29626 | P80: =OFFSET(P82,$H80,0) -> 0.29626 | Q80: =OFFSET(Q82,$H80,0) -> 0.29626 | R80: =OFFSET(R82,$H80,0) -> 0.29626 | S80: =OFFSET(S82,$H80,0) -> 0.29626
H82: unit
F83: Street | H83: $/Gal | O83: =O85 -> 0.26626 | P83: =P85 -> 0.26626 | Q83: =Q85 -> 0.26626 | R83: =R85 -> 0.26626 | S83: =S85 -> 0.26626
F84: Bear | H84: $/Gal | O84: =O85-0.03 -> 0.23626 | P84: =P85-0.03 -> 0.23626 | Q84: =Q85-0.03 -> 0.23626 | R84: =R85-0.03 -> 0.23626 | S84: =S85-0.03 -> 0.23626
F85: Base | H85: $/Gal | O85: 0.26626 | P85: =O85+U85 -> 0.26626 | Q85: =P85+V85 -> 0.26626 | R85: =Q85+W85 -> 0.26626 | S85: =R85+X85 -> 0.26626
F86: Bull | H86: $/Gal | O86: =O85+0.03 -> 0.29626 | P86: =P85+0.03 -> 0.29626 | Q86: =Q85+0.03 -> 0.29626 | R86: =R85+0.03 -> 0.29626 | S86: =S85+0.03 -> 0.29626
F89: Ethane Price Forecast | H89: ='Inputs & Assumptions'!L37 -> 1 | I89: {=_xlfn.IFS(H89= 1,"Street", H89=2,"Bear",H89=3,"Base",H89=4,"Bull")} -> Street | O89: =OFFSET(O91,$H89,0) -> 11.18292 | P89: =OFFSET(P91,$H89,0) -> 11.31088 | Q89: =OFFSET(Q91,$H89,0) -> 11.49596 | R89: =OFFSET(R91,$H89,0) -> 11.307905 | S89: =OFFSET(S91,$H89,0) -> 11.023425
H91: unit
F92: Street | H92: $/Bbl | O92: =O94 -> 11.18292 | P92: =P94 -> 11.31088 | Q92: =Q94 -> 11.49596 | R92: =R94 -> 11.307905 | S92: =S94 -> 11.023425
F93: Bear | H93: $/Bbl | O93: =O94-0.03 -> 11.15292 | P93: =P94-0.03 -> 11.28088 | Q93: =Q94-0.03 -> 11.46596 | R93: =R94-0.03 -> 11.277905 | S93: =S94-0.03 -> 10.993425
F94: Base | H94: $/Bbl | O94: =O85*42*(1+NAV!AU49) -> 11.18292 | P94: =O94+U94 -> 11.31088 | Q94: =P94+V94 -> 11.49596 | R94: =Q94+W94 -> 11.307905 | S94: =R94+X94 -> 11.023425 | U94: 0.12796 | V94: 0.18508 | W94: -0.188055 | X94: -0.28448
F95: Bull | H95: $/Bbl | O95: =O94+0.03 -> 11.21292 | P95: =P94+0.03 -> 11.34088 | Q95: =Q94+0.03 -> 11.52596 | R95: =R94+0.03 -> 11.337905 | S95: =S94+0.03 -> 11.053425
C98: d. | D98: Butane price Forecast
F101: Butane Price Forecast | H101: ='Inputs & Assumptions'!L37 -> 1 | I101: {=_xlfn.IFS(H101= 1,"Street", H101=2,"Bear",H101=3,"Base",H101=4,"Bull")} -> Street | K101: Weight: | L101: 0.2 | O101: =OFFSET(O103,$H101,0) -> 0.85 | P101: =OFFSET(P103,$H101,0) -> 0.78746417 | Q101: =OFFSET(Q103,$H101,0) -> 0.867 | R101: =OFFSET(R103,$H101,0) -> 0.783 | S101: =OFFSET(S103,$H101,0) -> 0.746
H103: unit
F104: Street | H104: $/Gal | O104: =O106 -> 0.85 | P104: =P106 -> 0.78746417 | Q104: =Q106 -> 0.867 | R104: =R106 -> 0.783 | S104: =S106 -> 0.746
F105: Bear | H105: $/Gal | O105: =O106-0.03 -> 0.82 | P105: =P106-0.03 -> 0.75746417 | Q105: =Q106-0.03 -> 0.837 | R105: =R106-0.03 -> 0.753 | S105: =S106-0.03 -> 0.716
F106: Base | H106: $/Gal | O106: 0.85 | P106: 0.78746417 | Q106: 0.867 | R106: 0.783 | S106: 0.746
F107: Bull | H107: $/Gal | O107: =O106+0.03 -> 0.88 | P107: =P106+0.03 -> 0.81746417 | Q107: =Q106+0.03 -> 0.897 | R107: =R106+0.03 -> 0.813 | S107: =S106+0.03 -> 0.776
F110: Butane Price Forecast | H110: ='Inputs & Assumptions'!L37 -> 1 | I110: {=_xlfn.IFS(H110= 1,"Street", H110=2,"Bear",H110=3,"Base",H110=4,"Bull")} -> Street | O110: =OFFSET(O112,$H110,0) -> 35.7 | P110: =OFFSET(P112,$H110,0) -> 33.073495 | Q110: =OFFSET(Q112,$H110,0) -> 36.414 | R110: =OFFSET(R112,$H110,0) -> 32.886 | S110: =OFFSET(S112,$H110,0) -> 31.332
H112: unit
F113: Street | H113: $/Bbl | O113: =O115 -> 35.7 | P113: =P115 -> 33.073495 | Q113: =Q115 -> 36.414 | R113: =R115 -> 32.886 | S113: =S115 -> 31.332
F114: Bear | H114: $/Bbl | O114: =O115-0.03 -> 35.67 | P114: =P115-0.03 -> 33.043495 | Q114: =Q115-0.03 -> 36.384 | R114: =R115-0.03 -> 32.856 | S114: =S115-0.03 -> 31.302
F115: Base | H115: $/Bbl | O115: =O106*42*(1+NAV!AU49) -> 35.7 | P115: =O115+U115 -> 33.073495 | Q115: =P115+V115 -> 36.414 | R115: =Q115+W115 -> 32.886 | S115: =R115+X115 -> 31.332 | U115: -2.626505 | V115: 3.340505 | W115: -3.528 | X115: -1.554
F116: Bull | H116: $/Bbl | O116: =O115+0.03 -> 35.73 | P116: =P115+0.03 -> 33.103495 | Q116: =Q115+0.03 -> 36.444 | R116: =R115+0.03 -> 32.916 | S116: =S115+0.03 -> 31.362
C119: f. | D119: NGL basket Price Assumptions
F122: Basket Price Forecast | H122: ='Inputs & Assumptions'!L37 -> 1 | I122: {=_xlfn.IFS(H122= 1,"Street", H122=2,"Bear",H122=3,"Base",H122=4,"Bull")} -> Street | O122: =OFFSET(O124,$H122,0) -> 21.877916 | P122: =OFFSET(P124,$H122,0) -> 21.265247 | Q122: =OFFSET(Q124,$H122,0) -> 22.148911 | R122: =OFFSET(R124,$H122,0) -> 21.493231 | S122: =OFFSET(S124,$H122,0) -> 21.052987
H124: unit
F125: Street | H125: $/Bbl | O125: =O127 -> 21.877916 | P125: =P127 -> 21.265247 | Q125: =Q127 -> 22.148911 | R125: =R127 -> 21.493231 | S125: =S127 -> 21.052987
F126: Bear | H126: $/Bbl | O126: =O127-0.03 -> 21.847916 | P126: =P127-0.03 -> 21.235247 | Q126: =Q127-0.03 -> 22.118911 | R126: =R127-0.03 -> 21.463231 | S126: =S127-0.03 -> 21.022987
F127: Base | H127: $/Bbl | O127: =O47*$L$38+O68*$L$59+O89*$L$80+O110*$L$101 -> 21.877916 | P127: =P47*$L$38+P68*$L$59+P89*$L$80+P110*$L$101 -> 21.265247 | Q127: =Q47*$L$38+Q68*$L$59+Q89*$L$80+Q110*$L$101 -> 22.148911 | R127: =R47*$L$38+R68*$L$59+R89*$L$80+R110*$L$101 -> 21.493231 | S127: =S47*$L$38+S68*$L$59+S89*$L$80+S110*$L$101 -> 21.052987
F128: Bull | H128: $/Bbl | O128: =O127+0.03 -> 21.907916 | P128: =P127+0.03 -> 21.295247 | Q128: =Q127+0.03 -> 22.178911 | R128: =R127+0.03 -> 21.523231 | S128: =S127+0.03 -> 21.082987

Sheet PD Reserves
D2: =Cover!C5 -> Net Asset Value Model - Range Resources Corp. (NYSE:RRC)
D3: PD Reserves
D5: Currently Running Commodity Price case: | H5: {=_xlfn.IFS('Inputs & Assumptions'!L37= 1,"Street", 'Inputs & Assumptions'!L37=2,"Bear",'Inputs & Assumptions'!L37=3,"Base",'Inputs & Assumptions'!L37=4,"Bull")} -> Street
F10: Proved Developed Reserves - Production Schedule | K10: FY 2024 | L10: FY 2025 | M10: FY 2026 | N10: FY 2027 | O10: FY 2028 | P10: FY 2029 | Q10: FY 2030 | R10: FY 2031 | S10: FY 2032 | T10: FY 2033 | U10: FY 2034 | V10: FY 2035 | W10: FY 2036 | X10: FY 2037 | Y10: FY 2038 | Z10: FY 2039 | AA10: FY 2040 | AB10: FY 2041 | AC10: FY 2042 | AD10: FY 2043 | AE10: FY 2044 | AF10: FY 2045 | AG10: FY 2046 | AH10: FY 2047 | AI10: FY 2048 | AJ10: FY 2049 | AK10: FY 2050 | AL10: FY 2051 | AM10: FY 2052 | AN10: FY 2053 | AO10: FY 2054
G12: Days | K12: - | L12: 365 | M12: 365 | N12: 365 | O12: 366 | P12: 365 | Q12: 365 | R12: 365 | S12: 366 | T12: 365 | U12: 365 | V12: 365 | W12: 366 | X12: 365 | Y12: 365 | Z12: 365 | AA12: 366 | AB12: 365 | AC12: 365 | AD12: 365 | AE12: 366 | AF12: 365 | AG12: 365 | AH12: 365 | AI12: 366 | AJ12: 365 | AK12: 365 | AL12: 365 | AM12: 366 | AN12: 365 | AO12: 365
G13: Begninning reserves | K13: - | L13: ='Inputs & Assumptions'!$L$65 -> 11930793 | M13: =L16 -> 11158303 | N13: =M16 -> 10424438 | O13: =N16 -> 9727266.3 | P13: =O16 -> 9063138.4 | Q13: =P16 -> 8433940.8 | R13: =Q16 -> 7836203 | S13: =R16 -> 7268352.1 | T13: =S16 -> 6727415.8 | ... AO13: =AN16 -> 0
G14: Daily Production | K14: ='Inputs & Assumptions'!L66 -> 2227.8 | L14: =K14*(1-'Inputs & Assumptions'!$L$67) -> 2116.41 | M14: =L14*(1-'Inputs & Assumptions'!$L$67) -> 2010.5895 | N14: =M14*(1-'Inputs & Assumptions'!$L$67) -> 1910.06 | O14: =N14*(1-'Inputs & Assumptions'!$L$67) -> 1814.557 | P14: =O14*(1-'Inputs & Assumptions'!$L$67) -> 1723.8292 | Q14: =P14*(1-'Inputs & Assumptions'!$L$67) -> 1637.6377 | R14: =Q14*(1-'Inputs & Assumptions'!$L$67) -> 1555.7558 | S14: =R14*(1-'Inputs & Assumptions'!$L$67) -> 1477.968 | ... AO14: =AN14*(1-'Inputs & Assumptions'!$L$67) -> 478.17224
G15: Annual Production | K15: - | L15: =MIN(L14*L12,L13) -> 772489.65 | M15: =MIN(M14*M12,M13) -> 733865.17 | N15: =MIN(N14*N12,N13) -> 697171.91 | O15: =MIN(O14*O12,O13) -> 664127.87 | P15: =MIN(P14*P12,P13) -> 629197.65 | Q15: =MIN(Q14*Q12,Q13) -> 597737.77 | R15: =MIN(R14*R12,R13) -> 567850.88 | S15: =MIN(S14*S12,S13) -> 540936.3 | ... AO15: =MIN(AO14*AO12,AO13) -> 0
G16: Ending Reserves | K16: - | L16: =L13-L15 -> 11158303 | M16: =M13-M15 -> 10424438 | N16: =N13-N15 -> 9727266.3 | O16: =O13-O15 -> 9063138.4 | P16: =P13-P15 -> 8433940.8 | Q16: =Q13-Q15 -> 7836203 | R16: =R13-R15 -> 7268352.1 | S16: =S13-S15 -> 6727415.8 | ... AO16: =AO13-AO15 -> 0
F20: Proved Developed Reserves - Cash Flows
B22: 1. | C22: Net Production
G24: Total Mmcfe | L24: =L15 -> 772489.65 | M24: =M15 -> 733865.17 | N24: =N15 -> 697171.91 | O24: =O15 -> 664127.87 | P24: =P15 -> 629197.65 | Q24: =Q15 -> 597737.77 | R24: =R15 -> 567850.88 | S24: =S15 -> 540936.3 | ... AO24: =AO15 -> 0
G25: Gas Mmcf | L25: =L24*'Inputs & Assumptions'!$L$58 -> 529155.41 | M25: =M24*'Inputs & Assumptions'!$L$58 -> 502697.64 | N25: =N24*'Inputs & Assumptions'!$L$58 -> 477562.76 | O25: =O24*'Inputs & Assumptions'!$L$58 -> 454927.59 | P25: =P24*'Inputs & Assumptions'!$L$58 -> 431000.39 | Q25: =Q24*'Inputs & Assumptions'!$L$58 -> 409450.37 | R25: =R24*'Inputs & Assumptions'!$L$58 -> 388977.85 | S25: =S24*'Inputs & Assumptions'!$L$58 -> 370541.37 | ... AO25: =AO24*'Inputs & Assumptions'!$L$58 -> 0
G26: NGL MBbl | L26: =L24*'Inputs & Assumptions'!$L$59/'Inputs & Assumptions'!$L$35 -> 38444.235 | M26: =M24*'Inputs & Assumptions'!$L$59/'Inputs & Assumptions'!$L$35 -> 36522.023 | N26: =N24*'Inputs & Assumptions'!$L$59/'Inputs & Assumptions'!$L$35 -> 34695.922 | O26: =O24*'Inputs & Assumptions'!$L$59/'Inputs & Assumptions'!$L$35 -> 33051.43 | P26: =P24*'Inputs & Assumptions'!$L$59/'Inputs & Assumptions'!$L$35 -> 31313.07 | Q26: =Q24*'Inputs & Assumptions'!$L$59/'Inputs & Assumptions'!$L$35 -> 29747.416 | R26: =R24*'Inputs & Assumptions'!$L$59/'Inputs & Assumptions'!$L$35 -> 28260.045 | S26: =S24*'Inputs & Assumptions'!$L$59/'Inputs & Assumptions'!$L$35 -> 26920.597 | ... AO26: =AO24*'Inputs & Assumptions'!$L$59/'Inputs & Assumptions'!$L$35 -> 0
G27: Oil MBbl | L27: =L24*'Inputs & Assumptions'!$L$60/'Inputs & Assumptions'!$L$35 -> 2111.4717 | M27: =M24*'Inputs & Assumptions'!$L$60/'Inputs & Assumptions'!$L$35 -> 2005.8981 | N27: =N24*'Inputs & Assumptions'!$L$60/'Inputs & Assumptions'!$L$35 -> 1905.6032 | O27: =O24*'Inputs & Assumptions'!$L$60/'Inputs & Assumptions'!$L$35 -> 1815.2828 | P27: =P24*'Inputs & Assumptions'!$L$60/'Inputs & Assumptions'!$L$35 -> 1719.8069 | Q27: =Q24*'Inputs & Assumptions'!$L$60/'Inputs & Assumptions'!$L$35 -> 1633.8166 | R27: =R24*'Inputs & Assumptions'!$L$60/'Inputs & Assumptions'!$L$35 -> 1552.1257 | S27: =S24*'Inputs & Assumptions'!$L$60/'Inputs & Assumptions'!$L$35 -> 1478.5592 | ... AO27: =AO24*'Inputs & Assumptions'!$L$60/'Inputs & Assumptions'!$L$35 -> 0
B29: 2. | C29: Revenue
C31: a. | D31: Natural Gas Revenue
G33: $ MM | L33: =L25*'Commodity Price Assumptions'!O10/1000 -> 1852.0439 | M33: =M25*'Commodity Price Assumptions'!P10/1000 -> 1930.3589 | N33: =N25*'Commodity Price Assumptions'!Q10/1000 -> 1838.6166 | O33: =O25*'Commodity Price Assumptions'!R10/1000 -> 1733.2741 | P33: =P25*'Commodity Price Assumptions'!$S$10/1000 -> 1655.0415 | Q33: =Q25*'Commodity Price Assumptions'!$S$10/1000 -> 1572.2894 | R33: =R25*'Commodity Price Assumptions'!$S$10/1000 -> 1493.6749 | S33: =S25*'Commodity Price Assumptions'!$S$10/1000 -> 1422.8788 | T33: =T25*'Commodity Price Assumptions'!$S$10/1000 -> 1348.0416 | U33: =U25*'Commodity Price Assumptions'!$S$10/1000 -> 1280.6396 | V33: =V25*'Commodity Price Assumptions'!$S$10/1000 -> 1216.6076 | W33: =W25*'Commodity Price Assumptions'!$S$10/1000 -> 1158.9437 | ... AO33: =AO25*'Commodity Price Assumptions'!$S$10/1000 -> 0
C35: b. | D35: NGL Revenue
G37: $ MM | L37: =L26*'Commodity Price Assumptions'!O122/1000*'Inputs & Assumptions'!$L$36 -> 1370.96 | M37: =M26*'Commodity Price Assumptions'!P122/1000*'Inputs & Assumptions'!$L$36 -> 1265.9392 | N37: =N26*'Commodity Price Assumptions'!Q122/1000*'Inputs & Assumptions'!$L$36 -> 1252.6174 | O37: =O26*'Commodity Price Assumptions'!R122/1000*'Inputs & Assumptions'!$L$36 -> 1157.9227 | P37: =P26*'Commodity Price Assumptions'!$S$122/1000*'Inputs & Assumptions'!$L$36 -> 1074.5509 | Q37: =Q26*'Commodity Price Assumptions'!$S$122/1000*'Inputs & Assumptions'!$L$36 -> 1020.8233 | R37: =R26*'Commodity Price Assumptions'!$S$122/1000*'Inputs & Assumptions'!$L$36 -> 969.78215 | S37: =S26*'Commodity Price Assumptions'!$S$122/1000*'Inputs & Assumptions'!$L$36 -> 923.81713 | T37: =T26*'Commodity Price Assumptions'!$S$122/1000*'Inputs & Assumptions'!$L$36 -> 875.22839 | U37: =U26*'Commodity Price Assumptions'!$S$122/1000*'Inputs & Assumptions'!$L$36 -> 831.46697 | V37: =V26*'Commodity Price Assumptions'!$S$122/1000*'Inputs & Assumptions'!$L$36 -> 789.89362 | W37: =W26*'Commodity Price Assumptions'!$S$122/1000*'Inputs & Assumptions'!$L$36 -> 752.45483 | ... AO37: =AO26*'Commodity Price Assumptions'!$S$122/1000*'Inputs & Assumptions'!$L$36 -> 0
C39: c. | D39: Oil Revenue
G41: $ MM | L41: =L27*'Commodity Price Assumptions'!O23/1000 -> 136.70259 | M41: =M27*'Commodity Price Assumptions'!P23/1000 -> 117.85775 | N41: =N27*'Commodity Price Assumptions'!Q23/1000 -> 121.3107 | O41: =O27*'Commodity Price Assumptions'!R23/1000 -> 122.60275 | P41: =P27*'Commodity Price Assumptions'!$S$23/1000 -> 118.97435 | Q41: =Q27*'Commodity Price Assumptions'!$S$23/1000 -> 113.02563 | R41: =R27*'Commodity Price Assumptions'!$S$23/1000 -> 107.37435 | S41: =S27*'Commodity Price Assumptions'!$S$23/1000 -> 102.2851 | T41: =T27*'Commodity Price Assumptions'!$S$23/1000 -> 96.905352 | U41: =U27*'Commodity Price Assumptions'!$S$23/1000 -> 92.060084 | V41: =V27*'Commodity Price Assumptions'!$S$23/1000 -> 87.45708 | W41: =W27*'Commodity Price Assumptions'!$S$23/1000 -> 83.311854 | ... AO41: =AO27*'Commodity Price Assumptions'!$S$23/1000 -> 0
B44: 3. | C44: Expenses
C46: a. | D46: Production Taxes
E48: Per Unit Price | G48: $/Mcfe | L48: ='Inputs & Assumptions'!$L$73 -> 0.04 | M48: ='Inputs & Assumptions'!$L$73 -> 0.04 | N48: ='Inputs & Assumptions'!$L$73 -> 0.04 | O48: ='Inputs & Assumptions'!$L$73 -> 0.04 | P48: ='Inputs & Assumptions'!$L$73 -> 0.04 | Q48: ='Inputs & Assumptions'!$L$73 -> 0.04 | R48: ='Inputs & Assumptions'!$L$73 -> 0.04 | S48: ='Inputs & Assumptions'!$L$73 -> 0.04 | ... AO48: ='Inputs & Assumptions'!$L$73 -> 0.04
E50: Total | G50: $MM | L50: =L48*L24/1000 -> 30.899586 | M50: =M48*M24/1000 -> 29.354607 | N50: =N48*N24/1000 -> 27.886876 | O50: =O48*O24/1000 -> 26.565115 | P50: =P48*P24/1000 -> 25.167906 | Q50: =Q48*Q24/1000 -> 23.909511 | R50: =R48*R24/1000 -> 22.714035 | S50: =S48*S24/1000 -> 21.637452 | ... AO50: =AO48*AO24/1000 -> 0
C52: b. | D52: Lease Operating Expense (LOE)
E54: Per Unit Price | G54: $/Mcfe | L54: ='Inputs & Assumptions'!$L$74 -> 0.14 | M54: ='Inputs & Assumptions'!$L$74 -> 0.14 | N54: ='Inputs & Assumptions'!$L$74 -> 0.14 | O54: ='Inputs & Assumptions'!$L$74 -> 0.14 | P54: ='Inputs & Assumptions'!$L$74 -> 0.14 | Q54: ='Inputs & Assumptions'!$L$74 -> 0.14 | R54: ='Inputs & Assumptions'!$L$74 -> 0.14 | S54: ='Inputs & Assumptions'!$L$74 -> 0.14 | ... AO54: ='Inputs & Assumptions'!$L$74 -> 0.14
E56: Total | G56: $MM | L56: =L54*L24/1000 -> 108.14855 | M56: =M54*M24/1000 -> 102.74112 | N56: =N54*N24/1000 -> 97.604067 | O56: =O54*O24/1000 -> 92.977902 | P56: =P54*P24/1000 -> 88.087671 | Q56: =Q54*Q24/1000 -> 83.683287 | R56: =R54*R24/1000 -> 79.499123 | S56: =S54*S24/1000 -> 75.731082 | ... AO56: =AO54*AO24/1000 -> 0
C58: c. | D58: Transport Expense
E60: Per Unit Price | G60: $/Mcfe | L60: ='Inputs & Assumptions'!$L$75 -> 1.642 | M60: ='Inputs & Assumptions'!$L$75 -> 1.642 | N60: ='Inputs & Assumptions'!$L$75 -> 1.642 | O60: ='Inputs & Assumptions'!$L$75 -> 1.642 | P60: ='Inputs & Assumptions'!$L$75 -> 1.642 | Q60: ='Inputs & Assumptions'!$L$75 -> 1.642 | R60: ='Inputs & Assumptions'!$L$75 -> 1.642 | S60: ='Inputs & Assumptions'!$L$75 -> 1.642 | ... AO60: ='Inputs & Assumptions'!$L$75 -> 1.642
E62: Total | G62: $MM | L62: =L60*L24/1000 -> 1268.428 | M62: =M60*M24/1000 -> 1205.0066 | N62: =N60*N24/1000 -> 1144.7563 | O62: =O60*O24/1000 -> 1090.498 | P62: =P60*P24/1000 -> 1033.1425 | Q62: =Q60*Q24/1000 -> 981.48541 | R62: =R60*R24/1000 -> 932.41114 | S62: =S60*S24/1000 -> 888.21741 | ... AO62: =AO60*AO24/1000 -> 0
B65: 4. | C65: Cash Flows
E67: Cash Flow from Operations | L67: =SUM(L33:L41)-L62 -> 2091.2785 | M67: =SUM(M33:M41)-M62 -> 2109.1493 | N67: =SUM(N33:N41)-N62 -> 2067.7884 | O67: =SUM(O33:O41)-O62 -> 1923.3016 | P67: =SUM(P33:P41)-P62 -> 1815.4242 | Q67: =SUM(Q33:Q41)-Q62 -> 1724.653 | R67: =SUM(R33:R41)-R62 -> 1638.4203 | S67: =SUM(S33:S41)-S62 -> 1560.7637 | ... AO67: =SUM(AO33:AO41)-AO62 -> 0
E69: CapEx | L69: =(L24/$L$13)*'Inputs & Assumptions'!$L$78 -> 54.868804 | M69: =(M24/$L$13)*'Inputs & Assumptions'!$L$78 -> 52.125363 | N69: =(N24/$L$13)*'Inputs & Assumptions'!$L$78 -> 49.519095 | O69: =(O24/$L$13)*'Inputs & Assumptions'!$L$78 -> 47.172026 | P69: =(P24/$L$13)*'Inputs & Assumptions'!$L$78 -> 44.690983 | Q69: =(Q24/$L$13)*'Inputs & Assumptions'!$L$78 -> 42.456434 | R69: =(R24/$L$13)*'Inputs & Assumptions'!$L$78 -> 40.333613 | S69: =(S24/$L$13)*'Inputs & Assumptions'!$L$78 -> 38.42191 | ... AO69: =(AO24/$L$13)*'Inputs & Assumptions'!$L$78 -> 0
E71: FCF | L71: =L67-L69 -> 2036.4097 | M71: =M67-M69 -> 2057.024 | N71: =N67-N69 -> 2018.2693 | O71: =O67-O69 -> 1876.1296 | P71: =P67-P69 -> 1770.7332 | Q71: =Q67-Q69 -> 1682.1965 | R71: =R67-R69 -> 1598.0867 | S71: =S67-S69 -> 1522.3418 | ... AO71: =AO67-AO69 -> 0
B73: 5. | C73: Discounted Cash Flow
E75: Year | L75: 1 | M75: 2 | N75: 3 | O75: 4 | P75: 5 | Q75: 6 | R75: 7 | S75: 8 | T75: 9 | U75: 10 | V75: 11 | W75: 12 | X75: 13 | Y75: 14 | Z75: 15 | AA75: 16 | AB75: 17 | AC75: 18 | AD75: 19 | AE75: 20 | AF75: 21 | AG75: 22 | AH75: 23 | AI75: 24 | AJ75: 25 | AK75: 26 | AL75: 27 | AM75: 28 | AN75: 29 | AO75: 30
E77: Discount Factor | L77: =1/((1+'Inputs & Assumptions'!$L$40)^('PD Reserves'!L75-1)) -> 1 | M77: =1/((1+'Inputs & Assumptions'!$L$40)^('PD Reserves'!M75-1)) -> 0.92253222 | N77: =1/((1+'Inputs & Assumptions'!$L$40)^('PD Reserves'!N75-1)) -> 0.85106569 | O77: =1/((1+'Inputs & Assumptions'!$L$40)^('PD Reserves'!O75-1)) -> 0.78513552 | P77: =1/((1+'Inputs & Assumptions'!$L$40)^('PD Reserves'!P75-1)) -> 0.72431282 | Q77: =1/((1+'Inputs & Assumptions'!$L$40)^('PD Reserves'!Q75-1)) -> 0.66820191 | R77: =1/((1+'Inputs & Assumptions'!$L$40)^('PD Reserves'!R75-1)) -> 0.61643779 | S77: =1/((1+'Inputs & Assumptions'!$L$40)^('PD Reserves'!S75-1)) -> 0.56868372 | ... AO77: =1/((1+'Inputs & Assumptions'!$L$40)^('PD Reserves'!AO75-1)) -> 0.096486095
E79: DCF | G79: $MM | L79: =L71*L77 -> 2036.4097 | M79: =M71*M77 -> 1897.6709 | N79: =N71*N77 -> 1717.6798 | O79: =O71*O77 -> 1473.016 | P79: =P71*P77 -> 1282.5647 | Q79: =Q71*Q77 -> 1124.0469 | R79: =R71*R77 -> 985.12103 | S79: =S71*S77 -> 865.73098 | ... AO79: =AO71*AO77 -> 0
E81: PV | G81: $MM | L81: =SUM(L79:AO79) -> 17113.522

Sheet PUD Reserves
D2: =Cover!C5 -> Net Asset Value Model - Range Resources Corp. (NYSE:RRC)
D3: PUD Reserves
D5: Currently Running Commodity Price case: | H5: {=_xlfn.IFS('Inputs & Assumptions'!L37= 1,"Street", 'Inputs & Assumptions'!L37=2,"Bear",'Inputs & Assumptions'!L37=3,"Base",'Inputs & Assumptions'!L37=4,"Bull")} -> Street
F10: Proved Undeveloped Reserves - Production Schedule | L10: FY 2025 | M10: FY 2026 | N10: FY 2027 | O10: FY 2028 | P10: FY 2029 | Q10: FY 2030 | R10: FY 2031 | S10: FY 2032 | T10: FY 2033 | U10: FY 2034 | V10: FY 2035 | W10: FY 2036 | X10: FY 2037 | Y10: FY 2038 | Z10: FY 2039 | AA10: FY 2040 | AB10: FY 2041 | AC10: FY 2042 | AD10: FY 2043 | AE10: FY 2044 | AF10: FY 2045 | AG10: FY 2046 | AH10: FY 2047 | AI10: FY 2048 | AJ10: FY 2049 | AK10: FY 2050 | AL10: FY 2051 | AM10: FY 2052 | AN10: FY 2053 | AO10: FY 2054 | AP10: FY 2055 | AQ10: FY 2056 | AR10: FY 2057 | AS10: FY 2058 | AT10: FY 2059 | AU10: FY 2060 | AV10: FY 2061 | AW10: FY 2062 | AX10: FY 2063 | AY10: FY 2064
G11: Period | J11: Total | L11: 1 | M11: 2 | N11: 3 | O11: 4 | P11: 5 | Q11: 6 | R11: 7 | S11: 8 | T11: 9 | U11: 10 | V11: 11 | W11: 12 | X11: 13 | Y11: 14 | Z11: 15 | AA11: 16 | AB11: 17 | AC11: 18 | AD11: 19 | AE11: 20 | AF11: 21 | AG11: 22 | AH11: 23 | AI11: 24 | AJ11: 25 | AK11: 26 | AL11: 27 | AM11: 28 | AN11: 29 | AO11: 30 | AP11: 31 | AQ11: 32 | AR11: 33 | AS11: 34 | AT11: 35 | AU11: 35 | AV11: 35 | AW11: 35 | AX11: 35 | AY11: 35
G12: Days | L12: 365 | M12: 365 | N12: 365 | O12: 366 | P12: 365 | Q12: 365 | R12: 365 | S12: 366 | T12: 365 | U12: 365 | V12: 365 | W12: 366 | X12: 365 | Y12: 365 | Z12: 365 | AA12: 366 | AB12: 365 | AC12: 365 | AD12: 365 | AE12: 366 | AF12: 365 | AG12: 365 | AH12: 365 | AI12: 366 | AJ12: 365 | AK12: 365 | AL12: 365 | AM12: 366 | AN12: 365 | AO12: 365 | AP12: 365 | AQ12: 366 | AR12: 365 | AS12: 365 | AT12: 365 | AU12: 366 | AV12: 365 | AW12: 365 | AX12: 365 | AY12: 366
H13: Gas MMcf | J13: =SUM(L13:AO13) -> 10275 | L13: =L16*'Inputs & Assumptions'!$L$58 -> 1284.375 | M13: =M16*'Inputs & Assumptions'!$L$58 -> 822 | N13: =N16*'Inputs & Assumptions'!$L$58 -> 690.48 | O13: =O16*'Inputs & Assumptions'!$L$58 -> 600.7176 | P13: =P16*'Inputs & Assumptions'!$L$58 -> 540.64584 | Q13: =Q16*'Inputs & Assumptions'!$L$58 -> 486.58126 | R13: =R16*'Inputs & Assumptions'!$L$58 -> 442.78894 | S13: =S16*'Inputs & Assumptions'!$L$58 -> 407.36583 | ... AY13: =AY16*'Inputs & Assumptions'!$L$58 -> 0
H14: NGL MBbl | J14: =SUM(L14:AO14) -> 746.5 | L14: =L16*'Inputs & Assumptions'!$L$59/'Inputs & Assumptions'!$L$35 -> 93.3125 | M14: =M16*'Inputs & Assumptions'!$L$59/'Inputs & Assumptions'!$L$35 -> 59.72 | N14: =N16*'Inputs & Assumptions'!$L$59/'Inputs & Assumptions'!$L$35 -> 50.1648 | O14: =O16*'Inputs & Assumptions'!$L$59/'Inputs & Assumptions'!$L$35 -> 43.643376 | P14: =P16*'Inputs & Assumptions'!$L$59/'Inputs & Assumptions'!$L$35 -> 39.279038 | Q14: =Q16*'Inputs & Assumptions'!$L$59/'Inputs & Assumptions'!$L$35 -> 35.351135 | R14: =R16*'Inputs & Assumptions'!$L$59/'Inputs & Assumptions'!$L$35 -> 32.169532 | S14: =S16*'Inputs & Assumptions'!$L$59/'Inputs & Assumptions'!$L$35 -> 29.59597 | ... AY14: =AY16*'Inputs & Assumptions'!$L$59/'Inputs & Assumptions'!$L$35 -> 0
H15: Oil MBbl | J15: =SUM(L15:AO15) -> 41 | L15: =L16*'Inputs & Assumptions'!$L$60/'Inputs & Assumptions'!$L$35 -> 5.125 | M15: =M16*'Inputs & Assumptions'!$L$60/'Inputs & Assumptions'!$L$35 -> 3.28 | N15: =N16*'Inputs & Assumptions'!$L$60/'Inputs & Assumptions'!$L$35 -> 2.7552 | O15: =O16*'Inputs & Assumptions'!$L$60/'Inputs & Assumptions'!$L$35 -> 2.397024 | P15: =P16*'Inputs & Assumptions'!$L$60/'Inputs & Assumptions'!$L$35 -> 2.1573216 | Q15: =Q16*'Inputs & Assumptions'!$L$60/'Inputs & Assumptions'!$L$35 -> 1.9415894 | R15: =R16*'Inputs & Assumptions'!$L$60/'Inputs & Assumptions'!$L$35 -> 1.7668464 | S15: =S16*'Inputs & Assumptions'!$L$60/'Inputs & Assumptions'!$L$35 -> 1.6254987 | ... AY15: =AY16*'Inputs & Assumptions'!$L$60/'Inputs & Assumptions'!$L$35 -> 0
G16: Total MMcfe | J16: =SUM(L16:AO16) -> 15000 | L16: =MIN('Inputs & Assumptions'!$L$85,'Inputs & Assumptions'!$L$90*L12) -> 1875 | M16: =MIN(L16*(1-M17),'Inputs & Assumptions'!$L$85-SUM($L$16:L16)) -> 1200 | N16: =MIN(M16*(1-N17),'Inputs & Assumptions'!$L$85-SUM($L$16:M16)) -> 1008 | O16: =MIN(N16*(1-O17),'Inputs & Assumptions'!$L$85-SUM($L$16:N16)) -> 876.96 | P16: =MIN(O16*(1-P17),'Inputs & Assumptions'!$L$85-SUM($L$16:O16)) -> 789.264 | Q16: =MIN(P16*(1-Q17),'Inputs & Assumptions'!$L$85-SUM($L$16:P16)) -> 710.3376 | R16: =MIN(Q16*(1-R17),'Inputs & Assumptions'!$L$85-SUM($L$16:Q16)) -> 646.40722 | S16: =MIN(R16*(1-S17),'Inputs & Assumptions'!$L$85-SUM($L$16:R16)) -> 594.69464 | T16: =MIN(S16*(1-T17),'Inputs & Assumptions'!$L$85-SUM($L$16:S16)) -> 553.06601 | ... AY16: =MIN(AX16*(1-AY17),'Inputs & Assumptions'!$L$85-SUM($L$16:AX16)) -> 0
G17: Decline Rate | M17: 0.36 | N17: 0.16 | O17: 0.13 | P17: 0.1 | Q17: 0.1 | R17: 0.09 | S17: 0.08 | T17: 0.07 | U17: 0.06 | V17: 0.05 | W17: 0.05 | X17: 0.05 | Y17: 0.05 | Z17: 0.04 | AA17: 0.04 | AB17: 0.04 | AC17: 0.04 | AD17: 0.04 | AE17: 0.04 | AF17: 0.04 | AG17: 0.04 | AH17: 0.04 | AI17: 0.04 | AJ17: 0.04 | AK17: 0.04 | AL17: 0.04 | AM17: 0.04 | AN17: 0.04 | AO17: 0.04 | AP17: 0.04 | AQ17: 0.04 | AR17: 0.04 | AS17: 0.04 | AT17: 0.04 | AU17: 1.04 | AV17: 2.04 | AW17: 3.04 | AX17: 4.04 | AY17: 5.04
B19: 1. | C19: Annual PUD Depletion
G22: Period | L22: 1 | M22: 2 | N22: 3 | O22: 4 | P22: 5 | Q22: 6 | R22: 7 | S22: 8 | T22: 9 | U22: 10 | V22: 11 | W22: 12 | X22: 13 | Y22: 14 | Z22: 15 | AA22: 16 | AB22: 17 | AC22: 18 | AD22: 19 | AE22: 20 | AF22: 21 | AG22: 22 | AH22: 23 | AI22: 24 | AJ22: 25 | AK22: 26 | AL22: 27 | AM22: 28 | AN22: 29 | AO22: 30 | AP22: Total
G23: Net Wells Drilled | L23: 55 | M23: 55 | N23: 55 | O23: 55 | P23: 55 | Q23: 55 | R23: 55 | S23: 28.378867 | T23: 0 | U23: 0 | V23: 0 | W23: 0 | X23: 0 | Y23: 0 | Z23: 0 | AA23: 0 | AB23: 0 | AC23: 0 | AD23: 0 | AE23: 0 | AF23: 0 | AG23: 0 | AH23: 0 | AI23: 0 | AJ23: 0 | AK23: 0 | AL23: 0 | AM23: 0 | AN23: 0 | AO23: 0
G24: Total D&C costs | L24: =L23*'Inputs & Assumptions'!$L$92 -> 563.75 | M24: =M23*'Inputs & Assumptions'!$L$92 -> 563.75 | N24: =N23*'Inputs & Assumptions'!$L$92 -> 563.75 | O24: =O23*'Inputs & Assumptions'!$L$92 -> 563.75 | P24: =P23*'Inputs & Assumptions'!$L$92 -> 563.75 | Q24: =Q23*'Inputs & Assumptions'!$L$92 -> 563.75 | R24: =R23*'Inputs & Assumptions'!$L$92 -> 563.75 | S24: =S23*'Inputs & Assumptions'!$L$92 -> 290.88338 | ... AO24: =AO23*'Inputs & Assumptions'!$L$92 -> 0 | AP24: =SUM(L24:S24) -> 4237.1334
G27: PUD MMcfe per year | K27: Period | L27: =IF($K28<L$22,0,AVERAGE(OFFSET($I$16,,$K28-L$22+3)*L$23,OFFSET($I$16,0,$K28-L$22+2)*L$23)) -> 51562.5 | M27: =IF($K28<M$22,0,AVERAGE(OFFSET($I$16,,$K28-M$22+3)*M$23,OFFSET($I$16,0,$K28-M$22+2)*M$23)) -> 0 | N27: =IF($K28<N$22,0,AVERAGE(OFFSET($I$16,,$K28-N$22+3)*N$23,OFFSET($I$16,0,$K28-N$22+2)*N$23)) -> 0 | O27: =IF($K28<O$22,0,AVERAGE(OFFSET($I$16,,$K28-O$22+3)*O$23,OFFSET($I$16,0,$K28-O$22+2)*O$23)) -> 0 | P27: =IF($K28<P$22,0,AVERAGE(OFFSET($I$16,,$K28-P$22+3)*P$23,OFFSET($I$16,0,$K28-P$22+2)*P$23)) -> 0 | Q27: =IF($K28<Q$22,0,AVERAGE(OFFSET($I$16,,$K28-Q$22+3)*Q$23,OFFSET($I$16,0,$K28-Q$22+2)*Q$23)) -> 0 | R27: =IF($K28<R$22,0,AVERAGE(OFFSET($I$16,,$K28-R$22+3)*R$23,OFFSET($I$16,0,$K28-R$22+2)*R$23)) -> 0 | S27: =IF($K28<S$22,0,AVERAGE(OFFSET($I$16,,$K28-S$22+3)*S$23,OFFSET($I$16,0,$K28-S$22+2)*S$23)) -> 0 | ... AO27: =IF($K28<AO$22,0,AVERAGE(OFFSET($I$16,,$K28-AO$22+3)*AO$23,OFFSET($I$16,0,$K28-AO$22+2)*AO$23)) -> 0 | AP27: =SUM(L27:AI27) -> 51562.5
K28: 1 | L28: =IF($K29<L$22,0,AVERAGE(OFFSET($I$16,,$K29-L$22+3)*L$23,OFFSET($I$16,0,$K29-L$22+2)*L$23)) -> 84562.5 | M28: =IF($K29<M$22,0,AVERAGE(OFFSET($I$16,,$K29-M$22+3)*M$23,OFFSET($I$16,0,$K29-M$22+2)*M$23)) -> 51562.5 | N28: =IF($K29<N$22,0,AVERAGE(OFFSET($I$16,,$K29-N$22+3)*N$23,OFFSET($I$16,0,$K29-N$22+2)*N$23)) -> 0 | O28: =IF($K29<O$22,0,AVERAGE(OFFSET($I$16,,$K29-O$22+3)*O$23,OFFSET($I$16,0,$K29-O$22+2)*O$23)) -> 0 | P28: =IF($K29<P$22,0,AVERAGE(OFFSET($I$16,,$K29-P$22+3)*P$23,OFFSET($I$16,0,$K29-P$22+2)*P$23)) -> 0 | Q28: =IF($K29<Q$22,0,AVERAGE(OFFSET($I$16,,$K29-Q$22+3)*Q$23,OFFSET($I$16,0,$K29-Q$22+2)*Q$23)) -> 0 | R28: =IF($K29<R$22,0,AVERAGE(OFFSET($I$16,,$K29-R$22+3)*R$23,OFFSET($I$16,0,$K29-R$22+2)*R$23)) -> 0 | S28: =IF($K29<S$22,0,AVERAGE(OFFSET($I$16,,$K29-S$22+3)*S$23,OFFSET($I$16,0,$K29-S$22+2)*S$23)) -> 0 | ... AO28: =IF($K29<AO$22,0,AVERAGE(OFFSET($I$16,,$K29-AO$22+3)*AO$23,OFFSET($I$16,0,$K29-AO$22+2)*AO$23)) -> 0 | AP28: =SUM(L28:AI28) -> 136125
K29: 2 | L29: =IF($K30<L$22,0,AVERAGE(OFFSET($I$16,,$K30-L$22+3)*L$23,OFFSET($I$16,0,$K30-L$22+2)*L$23)) -> 60720 | M29: =IF($K30<M$22,0,AVERAGE(OFFSET($I$16,,$K30-M$22+3)*M$23,OFFSET($I$16,0,$K30-M$22+2)*M$23)) -> 84562.5 | N29: =IF($K30<N$22,0,AVERAGE(OFFSET($I$16,,$K30-N$22+3)*N$23,OFFSET($I$16,0,$K30-N$22+2)*N$23)) -> 51562.5 | O29: =IF($K30<O$22,0,AVERAGE(OFFSET($I$16,,$K30-O$22+3)*O$23,OFFSET($I$16,0,$K30-O$22+2)*O$23)) -> 0 | P29: =IF($K30<P$22,0,AVERAGE(OFFSET($I$16,,$K30-P$22+3)*P$23,OFFSET($I$16,0,$K30-P$22+2)*P$23)) -> 0 | Q29: =IF($K30<Q$22,0,AVERAGE(OFFSET($I$16,,$K30-Q$22+3)*Q$23,OFFSET($I$16,0,$K30-Q$22+2)*Q$23)) -> 0 | R29: =IF($K30<R$22,0,AVERAGE(OFFSET($I$16,,$K30-R$22+3)*R$23,OFFSET($I$16,0,$K30-R$22+2)*R$23)) -> 0 | S29: =IF($K30<S$22,0,AVERAGE(OFFSET($I$16,,$K30-S$22+3)*S$23,OFFSET($I$16,0,$K30-S$22+2)*S$23)) -> 0 | ... AO29: =IF($K30<AO$22,0,AVERAGE(OFFSET($I$16,,$K30-AO$22+3)*AO$23,OFFSET($I$16,0,$K30-AO$22+2)*AO$23)) -> 0 | AP29: =SUM(L29:AI29) -> 196845
K30: 3 | L30: =IF($K31<L$22,0,AVERAGE(OFFSET($I$16,,$K31-L$22+3)*L$23,OFFSET($I$16,0,$K31-L$22+2)*L$23)) -> 51836.4 | M30: =IF($K31<M$22,0,AVERAGE(OFFSET($I$16,,$K31-M$22+3)*M$23,OFFSET($I$16,0,$K31-M$22+2)*M$23)) -> 60720 | N30: =IF($K31<N$22,0,AVERAGE(OFFSET($I$16,,$K31-N$22+3)*N$23,OFFSET($I$16,0,$K31-N$22+2)*N$23)) -> 84562.5 | O30: =IF($K31<O$22,0,AVERAGE(OFFSET($I$16,,$K31-O$22+3)*O$23,OFFSET($I$16,0,$K31-O$22+2)*O$23)) -> 51562.5 | P30: =IF($K31<P$22,0,AVERAGE(OFFSET($I$16,,$K31-P$22+3)*P$23,OFFSET($I$16,0,$K31-P$22+2)*P$23)) -> 0 | Q30: =IF($K31<Q$22,0,AVERAGE(OFFSET($I$16,,$K31-Q$22+3)*Q$23,OFFSET($I$16,0,$K31-Q$22+2)*Q$23)) -> 0 | R30: =IF($K31<R$22,0,AVERAGE(OFFSET($I$16,,$K31-R$22+3)*R$23,OFFSET($I$16,0,$K31-R$22+2)*R$23)) -> 0 | S30: =IF($K31<S$22,0,AVERAGE(OFFSET($I$16,,$K31-S$22+3)*S$23,OFFSET($I$16,0,$K31-S$22+2)*S$23)) -> 0 | ... AO30: =IF($K31<AO$22,0,AVERAGE(OFFSET($I$16,,$K31-AO$22+3)*AO$23,OFFSET($I$16,0,$K31-AO$22+2)*AO$23)) -> 0 | AP30: =SUM(L30:AI30) -> 248681.4
K31: 4 | L31: =IF($K32<L$22,0,AVERAGE(OFFSET($I$16,,$K32-L$22+3)*L$23,OFFSET($I$16,0,$K32-L$22+2)*L$23)) -> 45821.16 | M31: =IF($K32<M$22,0,AVERAGE(OFFSET($I$16,,$K32-M$22+3)*M$23,OFFSET($I$16,0,$K32-M$22+2)*M$23)) -> 51836.4 | N31: =IF($K32<N$22,0,AVERAGE(OFFSET($I$16,,$K32-N$22+3)*N$23,OFFSET($I$16,0,$K32-N$22+2)*N$23)) -> 60720 | O31: =IF($K32<O$22,0,AVERAGE(OFFSET($I$16,,$K32-O$22+3)*O$23,OFFSET($I$16,0,$K32-O$22+2)*O$23)) -> 84562.5 | P31: =IF($K32<P$22,0,AVERAGE(OFFSET($I$16,,$K32-P$22+3)*P$23,OFFSET($I$16,0,$K32-P$22+2)*P$23)) -> 51562.5 | Q31: =IF($K32<Q$22,0,AVERAGE(OFFSET($I$16,,$K32-Q$22+3)*Q$23,OFFSET($I$16,0,$K32-Q$22+2)*Q$23)) -> 0 | R31: =IF($K32<R$22,0,AVERAGE(OFFSET($I$16,,$K32-R$22+3)*R$23,OFFSET($I$16,0,$K32-R$22+2)*R$23)) -> 0 | S31: =IF($K32<S$22,0,AVERAGE(OFFSET($I$16,,$K32-S$22+3)*S$23,OFFSET($I$16,0,$K32-S$22+2)*S$23)) -> 0 | ... AO31: =IF($K32<AO$22,0,AVERAGE(OFFSET($I$16,,$K32-AO$22+3)*AO$23,OFFSET($I$16,0,$K32-AO$22+2)*AO$23)) -> 0 | AP31: =SUM(L31:AI31) -> 294502.56
K32: 5 | L32: =IF($K33<L$22,0,AVERAGE(OFFSET($I$16,,$K33-L$22+3)*L$23,OFFSET($I$16,0,$K33-L$22+2)*L$23)) -> 41239.044 | M32: =IF($K33<M$22,0,AVERAGE(OFFSET($I$16,,$K33-M$22+3)*M$23,OFFSET($I$16,0,$K33-M$22+2)*M$23)) -> 45821.16 | N32: =IF($K33<N$22,0,AVERAGE(OFFSET($I$16,,$K33-N$22+3)*N$23,OFFSET($I$16,0,$K33-N$22+2)*N$23)) -> 51836.4 | O32: =IF($K33<O$22,0,AVERAGE(OFFSET($I$16,,$K33-O$22+3)*O$23,OFFSET($I$16,0,$K33-O$22+2)*O$23)) -> 60720 | P32: =IF($K33<P$22,0,AVERAGE(OFFSET($I$16,,$K33-P$22+3)*P$23,OFFSET($I$16,0,$K33-P$22+2)*P$23)) -> 84562.5 | Q32: =IF($K33<Q$22,0,AVERAGE(OFFSET($I$16,,$K33-Q$22+3)*Q$23,OFFSET($I$16,0,$K33-Q$22+2)*Q$23)) -> 51562.5 | R32: =IF($K33<R$22,0,AVERAGE(OFFSET($I$16,,$K33-R$22+3)*R$23,OFFSET($I$16,0,$K33-R$22+2)*R$23)) -> 0 | S32: =IF($K33<S$22,0,AVERAGE(OFFSET($I$16,,$K33-S$22+3)*S$23,OFFSET($I$16,0,$K33-S$22+2)*S$23)) -> 0 | ... AO32: =IF($K33<AO$22,0,AVERAGE(OFFSET($I$16,,$K33-AO$22+3)*AO$23,OFFSET($I$16,0,$K33-AO$22+2)*AO$23)) -> 0 | AP32: =SUM(L32:AI32) -> 335741.6
K33: 6 | L33: =IF($K34<L$22,0,AVERAGE(OFFSET($I$16,,$K34-L$22+3)*L$23,OFFSET($I$16,0,$K34-L$22+2)*L$23)) -> 37310.482 | M33: =IF($K34<M$22,0,AVERAGE(OFFSET($I$16,,$K34-M$22+3)*M$23,OFFSET($I$16,0,$K34-M$22+2)*M$23)) -> 41239.044 | N33: =IF($K34<N$22,0,AVERAGE(OFFSET($I$16,,$K34-N$22+3)*N$23,OFFSET($I$16,0,$K34-N$22+2)*N$23)) -> 45821.16 | O33: =IF($K34<O$22,0,AVERAGE(OFFSET($I$16,,$K34-O$22+3)*O$23,OFFSET($I$16,0,$K34-O$22+2)*O$23)) -> 51836.4 | P33: =IF($K34<P$22,0,AVERAGE(OFFSET($I$16,,$K34-P$22+3)*P$23,OFFSET($I$16,0,$K34-P$22+2)*P$23)) -> 60720 | Q33: =IF($K34<Q$22,0,AVERAGE(OFFSET($I$16,,$K34-Q$22+3)*Q$23,OFFSET($I$16,0,$K34-Q$22+2)*Q$23)) -> 84562.5 | R33: =IF($K34<R$22,0,AVERAGE(OFFSET($I$16,,$K34-R$22+3)*R$23,OFFSET($I$16,0,$K34-R$22+2)*R$23)) -> 51562.5 | S33: =IF($K34<S$22,0,AVERAGE(OFFSET($I$16,,$K34-S$22+3)*S$23,OFFSET($I$16,0,$K34-S$22+2)*S$23)) -> 0 | ... AO33: =IF($K34<AO$22,0,AVERAGE(OFFSET($I$16,,$K34-AO$22+3)*AO$23,OFFSET($I$16,0,$K34-AO$22+2)*AO$23)) -> 0 | AP33: =SUM(L33:AI33) -> 373052.09
K34: 7 | L34: =IF($K35<L$22,0,AVERAGE(OFFSET($I$16,,$K35-L$22+3)*L$23,OFFSET($I$16,0,$K35-L$22+2)*L$23)) -> 34130.301 | M34: =IF($K35<M$22,0,AVERAGE(OFFSET($I$16,,$K35-M$22+3)*M$23,OFFSET($I$16,0,$K35-M$22+2)*M$23)) -> 37310.482 | N34: =IF($K35<N$22,0,AVERAGE(OFFSET($I$16,,$K35-N$22+3)*N$23,OFFSET($I$16,0,$K35-N$22+2)*N$23)) -> 41239.044 | O34: =IF($K35<O$22,0,AVERAGE(OFFSET($I$16,,$K35-O$22+3)*O$23,OFFSET($I$16,0,$K35-O$22+2)*O$23)) -> 45821.16 | P34: =IF($K35<P$22,0,AVERAGE(OFFSET($I$16,,$K35-P$22+3)*P$23,OFFSET($I$16,0,$K35-P$22+2)*P$23)) -> 51836.4 | Q34: =IF($K35<Q$22,0,AVERAGE(OFFSET($I$16,,$K35-Q$22+3)*Q$23,OFFSET($I$16,0,$K35-Q$22+2)*Q$23)) -> 60720 | R34: =IF($K35<R$22,0,AVERAGE(OFFSET($I$16,,$K35-R$22+3)*R$23,OFFSET($I$16,0,$K35-R$22+2)*R$23)) -> 84562.5 | S34: =IF($K35<S$22,0,AVERAGE(OFFSET($I$16,,$K35-S$22+3)*S$23,OFFSET($I$16,0,$K35-S$22+2)*S$23)) -> 26605.188 | ... AO34: =IF($K35<AO$22,0,AVERAGE(OFFSET($I$16,,$K35-AO$22+3)*AO$23,OFFSET($I$16,0,$K35-AO$22+2)*AO$23)) -> 0 | AP34: =SUM(L34:AI34) -> 382225.07
K35: 8 | L35: =IF($K36<L$22,0,AVERAGE(OFFSET($I$16,,$K36-L$22+3)*L$23,OFFSET($I$16,0,$K36-L$22+2)*L$23)) -> 31563.418 | M35: =IF($K36<M$22,0,AVERAGE(OFFSET($I$16,,$K36-M$22+3)*M$23,OFFSET($I$16,0,$K36-M$22+2)*M$23)) -> 34130.301 | N35: =IF($K36<N$22,0,AVERAGE(OFFSET($I$16,,$K36-N$22+3)*N$23,OFFSET($I$16,0,$K36-N$22+2)*N$23)) -> 37310.482 | O35: =IF($K36<O$22,0,AVERAGE(OFFSET($I$16,,$K36-O$22+3)*O$23,OFFSET($I$16,0,$K36-O$22+2)*O$23)) -> 41239.044 | P35: =IF($K36<P$22,0,AVERAGE(OFFSET($I$16,,$K36-P$22+3)*P$23,OFFSET($I$16,0,$K36-P$22+2)*P$23)) -> 45821.16 | Q35: =IF($K36<Q$22,0,AVERAGE(OFFSET($I$16,,$K36-Q$22+3)*Q$23,OFFSET($I$16,0,$K36-Q$22+2)*Q$23)) -> 51836.4 | R35: =IF($K36<R$22,0,AVERAGE(OFFSET($I$16,,$K36-R$22+3)*R$23,OFFSET($I$16,0,$K36-R$22+2)*R$23)) -> 60720 | S35: =IF($K36<S$22,0,AVERAGE(OFFSET($I$16,,$K36-S$22+3)*S$23,OFFSET($I$16,0,$K36-S$22+2)*S$23)) -> 43632.508 | ... AO35: =IF($K36<AO$22,0,AVERAGE(OFFSET($I$16,,$K36-AO$22+3)*AO$23,OFFSET($I$16,0,$K36-AO$22+2)*AO$23)) -> 0 | AP35: =SUM(L35:AI35) -> 346253.31
K36: 9 | L36: =IF($K37<L$22,0,AVERAGE(OFFSET($I$16,,$K37-L$22+3)*L$23,OFFSET($I$16,0,$K37-L$22+2)*L$23)) -> 29506.072 | M36: =IF($K37<M$22,0,AVERAGE(OFFSET($I$16,,$K37-M$22+3)*M$23,OFFSET($I$16,0,$K37-M$22+2)*M$23)) -> 31563.418 | N36: =IF($K37<N$22,0,AVERAGE(OFFSET($I$16,,$K37-N$22+3)*N$23,OFFSET($I$16,0,$K37-N$22+2)*N$23)) -> 34130.301 | O36: =IF($K37<O$22,0,AVERAGE(OFFSET($I$16,,$K37-O$22+3)*O$23,OFFSET($I$16,0,$K37-O$22+2)*O$23)) -> 37310.482 | P36: =IF($K37<P$22,0,AVERAGE(OFFSET($I$16,,$K37-P$22+3)*P$23,OFFSET($I$16,0,$K37-P$22+2)*P$23)) -> 41239.044 | Q36: =IF($K37<Q$22,0,AVERAGE(OFFSET($I$16,,$K37-Q$22+3)*Q$23,OFFSET($I$16,0,$K37-Q$22+2)*Q$23)) -> 45821.16 | R36: =IF($K37<R$22,0,AVERAGE(OFFSET($I$16,,$K37-R$22+3)*R$23,OFFSET($I$16,0,$K37-R$22+2)*R$23)) -> 51836.4 | S36: =IF($K37<S$22,0,AVERAGE(OFFSET($I$16,,$K37-S$22+3)*S$23,OFFSET($I$16,0,$K37-S$22+2)*S$23)) -> 31330.269 | ... AO36: =IF($K37<AO$22,0,AVERAGE(OFFSET($I$16,,$K37-AO$22+3)*AO$23,OFFSET($I$16,0,$K37-AO$22+2)*AO$23)) -> 0 | AP36: =SUM(L36:AI36) -> 302737.15
K37: 10 | L37: =IF($K38<L$22,0,AVERAGE(OFFSET($I$16,,$K38-L$22+3)*L$23,OFFSET($I$16,0,$K38-L$22+2)*L$23)) -> 27878.675 | M37: =IF($K38<M$22,0,AVERAGE(OFFSET($I$16,,$K38-M$22+3)*M$23,OFFSET($I$16,0,$K38-M$22+2)*M$23)) -> 29506.072 | N37: =IF($K38<N$22,0,AVERAGE(OFFSET($I$16,,$K38-N$22+3)*N$23,OFFSET($I$16,0,$K38-N$22+2)*N$23)) -> 31563.418 | O37: =IF($K38<O$22,0,AVERAGE(OFFSET($I$16,,$K38-O$22+3)*O$23,OFFSET($I$16,0,$K38-O$22+2)*O$23)) -> 34130.301 | P37: =IF($K38<P$22,0,AVERAGE(OFFSET($I$16,,$K38-P$22+3)*P$23,OFFSET($I$16,0,$K38-P$22+2)*P$23)) -> 37310.482 | Q37: =IF($K38<Q$22,0,AVERAGE(OFFSET($I$16,,$K38-Q$22+3)*Q$23,OFFSET($I$16,0,$K38-Q$22+2)*Q$23)) -> 41239.044 | R37: =IF($K38<R$22,0,AVERAGE(OFFSET($I$16,,$K38-R$22+3)*R$23,OFFSET($I$16,0,$K38-R$22+2)*R$23)) -> 45821.16 | S37: =IF($K38<S$22,0,AVERAGE(OFFSET($I$16,,$K38-S$22+3)*S$23,OFFSET($I$16,0,$K38-S$22+2)*S$23)) -> 26746.514 | ... AO37: =IF($K38<AO$22,0,AVERAGE(OFFSET($I$16,,$K38-AO$22+3)*AO$23,OFFSET($I$16,0,$K38-AO$22+2)*AO$23)) -> 0 | AP37: =SUM(L37:AI37) -> 274195.67
K38: 11 | L38: =IF($K39<L$22,0,AVERAGE(OFFSET($I$16,,$K39-L$22+3)*L$23,OFFSET($I$16,0,$K39-L$22+2)*L$23)) -> 26484.741 | M38: =IF($K39<M$22,0,AVERAGE(OFFSET($I$16,,$K39-M$22+3)*M$23,OFFSET($I$16,0,$K39-M$22+2)*M$23)) -> 27878.675 | N38: =IF($K39<N$22,0,AVERAGE(OFFSET($I$16,,$K39-N$22+3)*N$23,OFFSET($I$16,0,$K39-N$22+2)*N$23)) -> 29506.072 | O38: =IF($K39<O$22,0,AVERAGE(OFFSET($I$16,,$K39-O$22+3)*O$23,OFFSET($I$16,0,$K39-O$22+2)*O$23)) -> 31563.418 | P38: =IF($K39<P$22,0,AVERAGE(OFFSET($I$16,,$K39-P$22+3)*P$23,OFFSET($I$16,0,$K39-P$22+2)*P$23)) -> 34130.301 | Q38: =IF($K39<Q$22,0,AVERAGE(OFFSET($I$16,,$K39-Q$22+3)*Q$23,OFFSET($I$16,0,$K39-Q$22+2)*Q$23)) -> 37310.482 | R38: =IF($K39<R$22,0,AVERAGE(OFFSET($I$16,,$K39-R$22+3)*R$23,OFFSET($I$16,0,$K39-R$22+2)*R$23)) -> 41239.044 | S38: =IF($K39<S$22,0,AVERAGE(OFFSET($I$16,,$K39-S$22+3)*S$23,OFFSET($I$16,0,$K39-S$22+2)*S$23)) -> 23642.774 | ... AO38: =IF($K39<AO$22,0,AVERAGE(OFFSET($I$16,,$K39-AO$22+3)*AO$23,OFFSET($I$16,0,$K39-AO$22+2)*AO$23)) -> 0 | AP38: =SUM(L38:AI38) -> 251755.51
K39: 12 | L39: =IF($K40<L$22,0,AVERAGE(OFFSET($I$16,,$K40-L$22+3)*L$23,OFFSET($I$16,0,$K40-L$22+2)*L$23)) -> 25160.504 | M39: =IF($K40<M$22,0,AVERAGE(OFFSET($I$16,,$K40-M$22+3)*M$23,OFFSET($I$16,0,$K40-M$22+2)*M$23)) -> 26484.741 | N39: =IF($K40<N$22,0,AVERAGE(OFFSET($I$16,,$K40-N$22+3)*N$23,OFFSET($I$16,0,$K40-N$22+2)*N$23)) -> 27878.675 | O39: =IF($K40<O$22,0,AVERAGE(OFFSET($I$16,,$K40-O$22+3)*O$23,OFFSET($I$16,0,$K40-O$22+2)*O$23)) -> 29506.072 | P39: =IF($K40<P$22,0,AVERAGE(OFFSET($I$16,,$K40-P$22+3)*P$23,OFFSET($I$16,0,$K40-P$22+2)*P$23)) -> 31563.418 | Q39: =IF($K40<Q$22,0,AVERAGE(OFFSET($I$16,,$K40-Q$22+3)*Q$23,OFFSET($I$16,0,$K40-Q$22+2)*Q$23)) -> 34130.301 | R39: =IF($K40<R$22,0,AVERAGE(OFFSET($I$16,,$K40-R$22+3)*R$23,OFFSET($I$16,0,$K40-R$22+2)*R$23)) -> 37310.482 | S39: =IF($K40<S$22,0,AVERAGE(OFFSET($I$16,,$K40-S$22+3)*S$23,OFFSET($I$16,0,$K40-S$22+2)*S$23)) -> 21278.497 | ... AO39: =IF($K40<AO$22,0,AVERAGE(OFFSET($I$16,,$K40-AO$22+3)*AO$23,OFFSET($I$16,0,$K40-AO$22+2)*AO$23)) -> 0 | AP39: =SUM(L39:AI39) -> 233312.69
... K58: 31 | L58: =IF($K59<L$22,0,AVERAGE(OFFSET($I$16,,$K59-L$22+3)*L$23,OFFSET($I$16,0,$K59-L$22+2)*L$23)) -> 0 | M58: =IF($K59<M$22,0,AVERAGE(OFFSET($I$16,,$K59-M$22+3)*M$23,OFFSET($I$16,0,$K59-M$22+2)*M$23)) -> 0 | N58: =IF($K59<N$22,0,AVERAGE(OFFSET($I$16,,$K59-N$22+3)*N$23,OFFSET($I$16,0,$K59-N$22+2)*N$23)) -> 0 | O58: =IF($K59<O$22,0,AVERAGE(OFFSET($I$16,,$K59-O$22+3)*O$23,OFFSET($I$16,0,$K59-O$22+2)*O$23)) -> 5750.9822 | P58: =IF($K59<P$22,0,AVERAGE(OFFSET($I$16,,$K59-P$22+3)*P$23,OFFSET($I$16,0,$K59-P$22+2)*P$23)) -> 12600.468 | Q58: =IF($K59<Q$22,0,AVERAGE(OFFSET($I$16,,$K59-Q$22+3)*Q$23,OFFSET($I$16,0,$K59-Q$22+2)*Q$23)) -> 13984.367 | R58: =IF($K59<R$22,0,AVERAGE(OFFSET($I$16,,$K59-R$22+3)*R$23,OFFSET($I$16,0,$K59-R$22+2)*R$23)) -> 14567.049 | S58: =IF($K59<S$22,0,AVERAGE(OFFSET($I$16,,$K59-S$22+3)*S$23,OFFSET($I$16,0,$K59-S$22+2)*S$23)) -> 7829.4761 | ... AO58: =IF($K59<AO$22,0,AVERAGE(OFFSET($I$16,,$K59-AO$22+3)*AO$23,OFFSET($I$16,0,$K59-AO$22+2)*AO$23)) -> 0 | AP58: =SUM(L58:AI58) -> 54732.342
K59: 32 | L59: =IF($K60<L$22,0,AVERAGE(OFFSET($I$16,,$K60-L$22+3)*L$23,OFFSET($I$16,0,$K60-L$22+2)*L$23)) -> 0 | M59: =IF($K60<M$22,0,AVERAGE(OFFSET($I$16,,$K60-M$22+3)*M$23,OFFSET($I$16,0,$K60-M$22+2)*M$23)) -> 0 | N59: =IF($K60<N$22,0,AVERAGE(OFFSET($I$16,,$K60-N$22+3)*N$23,OFFSET($I$16,0,$K60-N$22+2)*N$23)) -> 0 | O59: =IF($K60<O$22,0,AVERAGE(OFFSET($I$16,,$K60-O$22+3)*O$23,OFFSET($I$16,0,$K60-O$22+2)*O$23)) -> 0 | P59: =IF($K60<P$22,0,AVERAGE(OFFSET($I$16,,$K60-P$22+3)*P$23,OFFSET($I$16,0,$K60-P$22+2)*P$23)) -> 5750.9822 | Q59: =IF($K60<Q$22,0,AVERAGE(OFFSET($I$16,,$K60-Q$22+3)*Q$23,OFFSET($I$16,0,$K60-Q$22+2)*Q$23)) -> 12600.468 | R59: =IF($K60<R$22,0,AVERAGE(OFFSET($I$16,,$K60-R$22+3)*R$23,OFFSET($I$16,0,$K60-R$22+2)*R$23)) -> 13984.367 | S59: =IF($K60<S$22,0,AVERAGE(OFFSET($I$16,,$K60-S$22+3)*S$23,OFFSET($I$16,0,$K60-S$22+2)*S$23)) -> 7516.297 | ... V59: =IF($K60<V$22,0,AVERAGE(OFFSET($I$16,,$K60-V$22+3)*V$23,OFFSET($I$16,0,$K60-V$22+2)*V$23)) -> 0 | W59: =IF($F60<W$22,0,AVERAGE(OFFSET($I$16,,$F60-W$22+3)*W$23,OFFSET($I$16,0,$F60-W$22+2)*W$23)) -> 0 | X59: =IF($F60<X$22,0,AVERAGE(OFFSET($I$16,,$F60-X$22+3)*X$23,OFFSET($I$16,0,$F60-X$22+2)*X$23)) -> 0 | Y59: =IF($F60<Y$22,0,AVERAGE(OFFSET($I$16,,$F60-Y$22+3)*Y$23,OFFSET($I$16,0,$F60-Y$22+2)*Y$23)) -> 0 | Z59: =IF($F60<Z$22,0,AVERAGE(OFFSET($I$16,,$F60-Z$22+3)*Z$23,OFFSET($I$16,0,$F60-Z$22+2)*Z$23)) -> 0 | AA59: =IF($F60<AA$22,0,AVERAGE(OFFSET($I$16,,$F60-AA$22+3)*AA$23,OFFSET($I$16,0,$F60-AA$22+2)*AA$23)) -> 0 | AB59: =IF($F60<AB$22,0,AVERAGE(OFFSET($I$16,,$F60-AB$22+3)*AB$23,OFFSET($I$16,0,$F60-AB$22+2)*AB$23)) -> 0 | AC59: =IF($F60<AC$22,0,AVERAGE(OFFSET($I$16,,$F60-AC$22+3)*AC$23,OFFSET($I$16,0,$F60-AC$22+2)*AC$23)) -> 0 | AD59: =IF($F60<AD$22,0,AVERAGE(OFFSET($I$16,,$F60-AD$22+3)*AD$23,OFFSET($I$16,0,$F60-AD$22+2)*AD$23)) -> 0 | ... AO59: =IF($F60<AO$22,0,AVERAGE(OFFSET($I$16,,$F60-AO$22+3)*AO$23,OFFSET($I$16,0,$F60-AO$22+2)*AO$23)) -> 0 | AP59: =SUM(L59:AI59) -> 39852.114
K60: 33 | L60: =IF($K61<L$22,0,AVERAGE(OFFSET($I$16,,$K61-L$22+3)*L$23,OFFSET($I$16,0,$K61-L$22+2)*L$23)) -> 0 | M60: =IF($K61<M$22,0,AVERAGE(OFFSET($I$16,,$K61-M$22+3)*M$23,OFFSET($I$16,0,$K61-M$22+2)*M$23)) -> 0 | N60: =IF($K61<N$22,0,AVERAGE(OFFSET($I$16,,$K61-N$22+3)*N$23,OFFSET($I$16,0,$K61-N$22+2)*N$23)) -> 0 | O60: =IF($K61<O$22,0,AVERAGE(OFFSET($I$16,,$K61-O$22+3)*O$23,OFFSET($I$16,0,$K61-O$22+2)*O$23)) -> 0 | P60: =IF($K61<P$22,0,AVERAGE(OFFSET($I$16,,$K61-P$22+3)*P$23,OFFSET($I$16,0,$K61-P$22+2)*P$23)) -> 0 | Q60: =IF($K61<Q$22,0,AVERAGE(OFFSET($I$16,,$K61-Q$22+3)*Q$23,OFFSET($I$16,0,$K61-Q$22+2)*Q$23)) -> 5750.9822 | R60: =IF($K61<R$22,0,AVERAGE(OFFSET($I$16,,$K61-R$22+3)*R$23,OFFSET($I$16,0,$K61-R$22+2)*R$23)) -> 12600.468 | S60: =IF($K61<S$22,0,AVERAGE(OFFSET($I$16,,$K61-S$22+3)*S$23,OFFSET($I$16,0,$K61-S$22+2)*S$23)) -> 7215.6451 | ... V60: =IF($K61<V$22,0,AVERAGE(OFFSET($I$16,,$K61-V$22+3)*V$23,OFFSET($I$16,0,$K61-V$22+2)*V$23)) -> 0 | W60: =IF($F61<W$22,0,AVERAGE(OFFSET($I$16,,$F61-W$22+3)*W$23,OFFSET($I$16,0,$F61-W$22+2)*W$23)) -> 0 | X60: =IF($F61<X$22,0,AVERAGE(OFFSET($I$16,,$F61-X$22+3)*X$23,OFFSET($I$16,0,$F61-X$22+2)*X$23)) -> 0 | Y60: =IF($F61<Y$22,0,AVERAGE(OFFSET($I$16,,$F61-Y$22+3)*Y$23,OFFSET($I$16,0,$F61-Y$22+2)*Y$23)) -> 0 | Z60: =IF($F61<Z$22,0,AVERAGE(OFFSET($I$16,,$F61-Z$22+3)*Z$23,OFFSET($I$16,0,$F61-Z$22+2)*Z$23)) -> 0 | AA60: =IF($F61<AA$22,0,AVERAGE(OFFSET($I$16,,$F61-AA$22+3)*AA$23,OFFSET($I$16,0,$F61-AA$22+2)*AA$23)) -> 0 | AB60: =IF($F61<AB$22,0,AVERAGE(OFFSET($I$16,,$F61-AB$22+3)*AB$23,OFFSET($I$16,0,$F61-AB$22+2)*AB$23)) -> 0 | AC60: =IF($F61<AC$22,0,AVERAGE(OFFSET($I$16,,$F61-AC$22+3)*AC$23,OFFSET($I$16,0,$F61-AC$22+2)*AC$23)) -> 0 | AD60: =IF($F61<AD$22,0,AVERAGE(OFFSET($I$16,,$F61-AD$22+3)*AD$23,OFFSET($I$16,0,$F61-AD$22+2)*AD$23)) -> 0 | ... AO60: =IF($F61<AO$22,0,AVERAGE(OFFSET($I$16,,$F61-AO$22+3)*AO$23,OFFSET($I$16,0,$F61-AO$22+2)*AO$23)) -> 0 | AP60: =SUM(L60:AI60) -> 25567.095
K61: 34 | L61: =IF($K62<L$22,0,AVERAGE(OFFSET($I$16,,$K62-L$22+3)*L$23,OFFSET($I$16,0,$K62-L$22+2)*L$23)) -> 0 | M61: =IF($K62<M$22,0,AVERAGE(OFFSET($I$16,,$K62-M$22+3)*M$23,OFFSET($I$16,0,$K62-M$22+2)*M$23)) -> 0 | N61: =IF($K62<N$22,0,AVERAGE(OFFSET($I$16,,$K62-N$22+3)*N$23,OFFSET($I$16,0,$K62-N$22+2)*N$23)) -> 0 | O61: =IF($K62<O$22,0,AVERAGE(OFFSET($I$16,,$K62-O$22+3)*O$23,OFFSET($I$16,0,$K62-O$22+2)*O$23)) -> 0 | P61: =IF($K62<P$22,0,AVERAGE(OFFSET($I$16,,$K62-P$22+3)*P$23,OFFSET($I$16,0,$K62-P$22+2)*P$23)) -> 0 | Q61: =IF($K62<Q$22,0,AVERAGE(OFFSET($I$16,,$K62-Q$22+3)*Q$23,OFFSET($I$16,0,$K62-Q$22+2)*Q$23)) -> 0 | R61: =IF($K62<R$22,0,AVERAGE(OFFSET($I$16,,$K62-R$22+3)*R$23,OFFSET($I$16,0,$K62-R$22+2)*R$23)) -> 5750.9822 | S61: =IF($K62<S$22,0,AVERAGE(OFFSET($I$16,,$K62-S$22+3)*S$23,OFFSET($I$16,0,$K62-S$22+2)*S$23)) -> 6501.5818 | ... V61: =IF($K62<V$22,0,AVERAGE(OFFSET($I$16,,$K62-V$22+3)*V$23,OFFSET($I$16,0,$K62-V$22+2)*V$23)) -> 0 | W61: =IF($F62<W$22,0,AVERAGE(OFFSET($I$16,,$F62-W$22+3)*W$23,OFFSET($I$16,0,$F62-W$22+2)*W$23)) -> 0 | X61: =IF($F62<X$22,0,AVERAGE(OFFSET($I$16,,$F62-X$22+3)*X$23,OFFSET($I$16,0,$F62-X$22+2)*X$23)) -> 0 | Y61: =IF($F62<Y$22,0,AVERAGE(OFFSET($I$16,,$F62-Y$22+3)*Y$23,OFFSET($I$16,0,$F62-Y$22+2)*Y$23)) -> 0 | Z61: =IF($F62<Z$22,0,AVERAGE(OFFSET($I$16,,$F62-Z$22+3)*Z$23,OFFSET($I$16,0,$F62-Z$22+2)*Z$23)) -> 0 | AA61: =IF($F62<AA$22,0,AVERAGE(OFFSET($I$16,,$F62-AA$22+3)*AA$23,OFFSET($I$16,0,$F62-AA$22+2)*AA$23)) -> 0 | AB61: =IF($F62<AB$22,0,AVERAGE(OFFSET($I$16,,$F62-AB$22+3)*AB$23,OFFSET($I$16,0,$F62-AB$22+2)*AB$23)) -> 0 | AC61: =IF($F62<AC$22,0,AVERAGE(OFFSET($I$16,,$F62-AC$22+3)*AC$23,OFFSET($I$16,0,$F62-AC$22+2)*AC$23)) -> 0 | AD61: =IF($F62<AD$22,0,AVERAGE(OFFSET($I$16,,$F62-AD$22+3)*AD$23,OFFSET($I$16,0,$F62-AD$22+2)*AD$23)) -> 0 | ... AO61: =IF($F62<AO$22,0,AVERAGE(OFFSET($I$16,,$F62-AO$22+3)*AO$23,OFFSET($I$16,0,$F62-AO$22+2)*AO$23)) -> 0 | AP61: =SUM(L61:AI61) -> 12252.564
K62: 35 | L62: =IF($K63<L$22,0,AVERAGE(OFFSET($I$16,,$K63-L$22+3)*L$23,OFFSET($I$16,0,$K63-L$22+2)*L$23)) -> 0 | M62: =IF($K63<M$22,0,AVERAGE(OFFSET($I$16,,$K63-M$22+3)*M$23,OFFSET($I$16,0,$K63-M$22+2)*M$23)) -> 0 | N62: =IF($K63<N$22,0,AVERAGE(OFFSET($I$16,,$K63-N$22+3)*N$23,OFFSET($I$16,0,$K63-N$22+2)*N$23)) -> 0 | O62: =IF($K63<O$22,0,AVERAGE(OFFSET($I$16,,$K63-O$22+3)*O$23,OFFSET($I$16,0,$K63-O$22+2)*O$23)) -> 0 | P62: =IF($K63<P$22,0,AVERAGE(OFFSET($I$16,,$K63-P$22+3)*P$23,OFFSET($I$16,0,$K63-P$22+2)*P$23)) -> 0 | Q62: =IF($K63<Q$22,0,AVERAGE(OFFSET($I$16,,$K63-Q$22+3)*Q$23,OFFSET($I$16,0,$K63-Q$22+2)*Q$23)) -> 0 | R62: =IF($K63<R$22,0,AVERAGE(OFFSET($I$16,,$K63-R$22+3)*R$23,OFFSET($I$16,0,$K63-R$22+2)*R$23)) -> 0 | S62: =IF($K63<S$22,0,AVERAGE(OFFSET($I$16,,$K63-S$22+3)*S$23,OFFSET($I$16,0,$K63-S$22+2)*S$23)) -> 2967.3883 | ... V62: =IF($K63<V$22,0,AVERAGE(OFFSET($I$16,,$K63-V$22+3)*V$23,OFFSET($I$16,0,$K63-V$22+2)*V$23)) -> 0 | W62: =IF($F63<W$22,0,AVERAGE(OFFSET($I$16,,$F63-W$22+3)*W$23,OFFSET($I$16,0,$F63-W$22+2)*W$23)) -> 0 | X62: =IF($F63<X$22,0,AVERAGE(OFFSET($I$16,,$F63-X$22+3)*X$23,OFFSET($I$16,0,$F63-X$22+2)*X$23)) -> 0 | Y62: =IF($F63<Y$22,0,AVERAGE(OFFSET($I$16,,$F63-Y$22+3)*Y$23,OFFSET($I$16,0,$F63-Y$22+2)*Y$23)) -> 0 | Z62: =IF($F63<Z$22,0,AVERAGE(OFFSET($I$16,,$F63-Z$22+3)*Z$23,OFFSET($I$16,0,$F63-Z$22+2)*Z$23)) -> 0 | AA62: =IF($F63<AA$22,0,AVERAGE(OFFSET($I$16,,$F63-AA$22+3)*AA$23,OFFSET($I$16,0,$F63-AA$22+2)*AA$23)) -> 0 | AB62: =IF($F63<AB$22,0,AVERAGE(OFFSET($I$16,,$F63-AB$22+3)*AB$23,OFFSET($I$16,0,$F63-AB$22+2)*AB$23)) -> 0 | AC62: =IF($F63<AC$22,0,AVERAGE(OFFSET($I$16,,$F63-AC$22+3)*AC$23,OFFSET($I$16,0,$F63-AC$22+2)*AC$23)) -> 0 | AD62: =IF($F63<AD$22,0,AVERAGE(OFFSET($I$16,,$F63-AD$22+3)*AD$23,OFFSET($I$16,0,$F63-AD$22+2)*AD$23)) -> 0 | ... AO62: =IF($F63<AO$22,0,AVERAGE(OFFSET($I$16,,$F63-AO$22+3)*AO$23,OFFSET($I$16,0,$F63-AO$22+2)*AO$23)) -> 0 | AP62: =SUM(L62:AI62) -> 2967.3883
K63: 36 | L63: =IF($K64<L$22,0,AVERAGE(OFFSET($I$16,,$K64-L$22+3)*L$23,OFFSET($I$16,0,$K64-L$22+2)*L$23)) -> 0 | M63: =IF($K64<M$22,0,AVERAGE(OFFSET($I$16,,$K64-M$22+3)*M$23,OFFSET($I$16,0,$K64-M$22+2)*M$23)) -> 0 | N63: =IF($K64<N$22,0,AVERAGE(OFFSET($I$16,,$K64-N$22+3)*N$23,OFFSET($I$16,0,$K64-N$22+2)*N$23)) -> 0 | O63: =IF($K64<O$22,0,AVERAGE(OFFSET($I$16,,$K64-O$22+3)*O$23,OFFSET($I$16,0,$K64-O$22+2)*O$23)) -> 0 | P63: =IF($K64<P$22,0,AVERAGE(OFFSET($I$16,,$K64-P$22+3)*P$23,OFFSET($I$16,0,$K64-P$22+2)*P$23)) -> 0 | Q63: =IF($K64<Q$22,0,AVERAGE(OFFSET($I$16,,$K64-Q$22+3)*Q$23,OFFSET($I$16,0,$K64-Q$22+2)*Q$23)) -> 0 | R63: =IF($K64<R$22,0,AVERAGE(OFFSET($I$16,,$K64-R$22+3)*R$23,OFFSET($I$16,0,$K64-R$22+2)*R$23)) -> 0 | S63: =IF($K64<S$22,0,AVERAGE(OFFSET($I$16,,$K64-S$22+3)*S$23,OFFSET($I$16,0,$K64-S$22+2)*S$23)) -> 0 | ... V63: =IF($K64<V$22,0,AVERAGE(OFFSET($I$16,,$K64-V$22+3)*V$23,OFFSET($I$16,0,$K64-V$22+2)*V$23)) -> 0 | W63: =IF($F64<W$22,0,AVERAGE(OFFSET($I$16,,$F64-W$22+3)*W$23,OFFSET($I$16,0,$F64-W$22+2)*W$23)) -> 0 | X63: =IF($F64<X$22,0,AVERAGE(OFFSET($I$16,,$F64-X$22+3)*X$23,OFFSET($I$16,0,$F64-X$22+2)*X$23)) -> 0 | Y63: =IF($F64<Y$22,0,AVERAGE(OFFSET($I$16,,$F64-Y$22+3)*Y$23,OFFSET($I$16,0,$F64-Y$22+2)*Y$23)) -> 0 | Z63: =IF($F64<Z$22,0,AVERAGE(OFFSET($I$16,,$F64-Z$22+3)*Z$23,OFFSET($I$16,0,$F64-Z$22+2)*Z$23)) -> 0 | AA63: =IF($F64<AA$22,0,AVERAGE(OFFSET($I$16,,$F64-AA$22+3)*AA$23,OFFSET($I$16,0,$F64-AA$22+2)*AA$23)) -> 0 | AB63: =IF($F64<AB$22,0,AVERAGE(OFFSET($I$16,,$F64-AB$22+3)*AB$23,OFFSET($I$16,0,$F64-AB$22+2)*AB$23)) -> 0 | AC63: =IF($F64<AC$22,0,AVERAGE(OFFSET($I$16,,$F64-AC$22+3)*AC$23,OFFSET($I$16,0,$F64-AC$22+2)*AC$23)) -> 0 | AD63: =IF($F64<AD$22,0,AVERAGE(OFFSET($I$16,,$F64-AD$22+3)*AD$23,OFFSET($I$16,0,$F64-AD$22+2)*AD$23)) -> 0 | ... AO63: =IF($F64<AO$22,0,AVERAGE(OFFSET($I$16,,$F64-AO$22+3)*AO$23,OFFSET($I$16,0,$F64-AO$22+2)*AO$23)) -> 0 | AP63: =SUM(L63:AI63) -> 0
K64: 37 | L64: =IF($K65<L$22,0,AVERAGE(OFFSET($I$16,,$K65-L$22+3)*L$23,OFFSET($I$16,0,$K65-L$22+2)*L$23)) -> 0 | M64: =IF($K65<M$22,0,AVERAGE(OFFSET($I$16,,$K65-M$22+3)*M$23,OFFSET($I$16,0,$K65-M$22+2)*M$23)) -> 0 | N64: =IF($K65<N$22,0,AVERAGE(OFFSET($I$16,,$K65-N$22+3)*N$23,OFFSET($I$16,0,$K65-N$22+2)*N$23)) -> 0 | O64: =IF($K65<O$22,0,AVERAGE(OFFSET($I$16,,$K65-O$22+3)*O$23,OFFSET($I$16,0,$K65-O$22+2)*O$23)) -> 0 | P64: =IF($K65<P$22,0,AVERAGE(OFFSET($I$16,,$K65-P$22+3)*P$23,OFFSET($I$16,0,$K65-P$22+2)*P$23)) -> 0 | Q64: =IF($K65<Q$22,0,AVERAGE(OFFSET($I$16,,$K65-Q$22+3)*Q$23,OFFSET($I$16,0,$K65-Q$22+2)*Q$23)) -> 0 | R64: =IF($K65<R$22,0,AVERAGE(OFFSET($I$16,,$K65-R$22+3)*R$23,OFFSET($I$16,0,$K65-R$22+2)*R$23)) -> 0 | S64: =IF($K65<S$22,0,AVERAGE(OFFSET($I$16,,$K65-S$22+3)*S$23,OFFSET($I$16,0,$K65-S$22+2)*S$23)) -> 0 | ... V64: =IF($K65<V$22,0,AVERAGE(OFFSET($I$16,,$K65-V$22+3)*V$23,OFFSET($I$16,0,$K65-V$22+2)*V$23)) -> 0 | W64: =IF($F65<W$22,0,AVERAGE(OFFSET($I$16,,$F65-W$22+3)*W$23,OFFSET($I$16,0,$F65-W$22+2)*W$23)) -> 0 | X64: =IF($F65<X$22,0,AVERAGE(OFFSET($I$16,,$F65-X$22+3)*X$23,OFFSET($I$16,0,$F65-X$22+2)*X$23)) -> 0 | Y64: =IF($F65<Y$22,0,AVERAGE(OFFSET($I$16,,$F65-Y$22+3)*Y$23,OFFSET($I$16,0,$F65-Y$22+2)*Y$23)) -> 0 | Z64: =IF($F65<Z$22,0,AVERAGE(OFFSET($I$16,,$F65-Z$22+3)*Z$23,OFFSET($I$16,0,$F65-Z$22+2)*Z$23)) -> 0 | AA64: =IF($F65<AA$22,0,AVERAGE(OFFSET($I$16,,$F65-AA$22+3)*AA$23,OFFSET($I$16,0,$F65-AA$22+2)*AA$23)) -> 0 | AB64: =IF($F65<AB$22,0,AVERAGE(OFFSET($I$16,,$F65-AB$22+3)*AB$23,OFFSET($I$16,0,$F65-AB$22+2)*AB$23)) -> 0 | AC64: =IF($F65<AC$22,0,AVERAGE(OFFSET($I$16,,$F65-AC$22+3)*AC$23,OFFSET($I$16,0,$F65-AC$22+2)*AC$23)) -> 0 | AD64: =IF($F65<AD$22,0,AVERAGE(OFFSET($I$16,,$F65-AD$22+3)*AD$23,OFFSET($I$16,0,$F65-AD$22+2)*AD$23)) -> 0 | ... AO64: =IF($F65<AO$22,0,AVERAGE(OFFSET($I$16,,$F65-AO$22+3)*AO$23,OFFSET($I$16,0,$F65-AO$22+2)*AO$23)) -> 0 | AP64: =SUM(L64:AI64) -> 0
K65: 38 | L65: =IF($K66<L$22,0,AVERAGE(OFFSET($I$16,,$K66-L$22+3)*L$23,OFFSET($I$16,0,$K66-L$22+2)*L$23)) -> 0 | M65: =IF($K66<M$22,0,AVERAGE(OFFSET($I$16,,$K66-M$22+3)*M$23,OFFSET($I$16,0,$K66-M$22+2)*M$23)) -> 0 | N65: =IF($K66<N$22,0,AVERAGE(OFFSET($I$16,,$K66-N$22+3)*N$23,OFFSET($I$16,0,$K66-N$22+2)*N$23)) -> 0 | O65: =IF($K66<O$22,0,AVERAGE(OFFSET($I$16,,$K66-O$22+3)*O$23,OFFSET($I$16,0,$K66-O$22+2)*O$23)) -> 0 | P65: =IF($K66<P$22,0,AVERAGE(OFFSET($I$16,,$K66-P$22+3)*P$23,OFFSET($I$16,0,$K66-P$22+2)*P$23)) -> 0 | Q65: =IF($K66<Q$22,0,AVERAGE(OFFSET($I$16,,$K66-Q$22+3)*Q$23,OFFSET($I$16,0,$K66-Q$22+2)*Q$23)) -> 0 | R65: =IF($K66<R$22,0,AVERAGE(OFFSET($I$16,,$K66-R$22+3)*R$23,OFFSET($I$16,0,$K66-R$22+2)*R$23)) -> 0 | S65: =IF($K66<S$22,0,AVERAGE(OFFSET($I$16,,$K66-S$22+3)*S$23,OFFSET($I$16,0,$K66-S$22+2)*S$23)) -> 0 | ... V65: =IF($K66<V$22,0,AVERAGE(OFFSET($I$16,,$K66-V$22+3)*V$23,OFFSET($I$16,0,$K66-V$22+2)*V$23)) -> 0 | W65: =IF($F66<W$22,0,AVERAGE(OFFSET($I$16,,$F66-W$22+3)*W$23,OFFSET($I$16,0,$F66-W$22+2)*W$23)) -> 0 | X65: =IF($F66<X$22,0,AVERAGE(OFFSET($I$16,,$F66-X$22+3)*X$23,OFFSET($I$16,0,$F66-X$22+2)*X$23)) -> 0 | Y65: =IF($F66<Y$22,0,AVERAGE(OFFSET($I$16,,$F66-Y$22+3)*Y$23,OFFSET($I$16,0,$F66-Y$22+2)*Y$23)) -> 0 | Z65: =IF($F66<Z$22,0,AVERAGE(OFFSET($I$16,,$F66-Z$22+3)*Z$23,OFFSET($I$16,0,$F66-Z$22+2)*Z$23)) -> 0 | AA65: =IF($F66<AA$22,0,AVERAGE(OFFSET($I$16,,$F66-AA$22+3)*AA$23,OFFSET($I$16,0,$F66-AA$22+2)*AA$23)) -> 0 | AB65: =IF($F66<AB$22,0,AVERAGE(OFFSET($I$16,,$F66-AB$22+3)*AB$23,OFFSET($I$16,0,$F66-AB$22+2)*AB$23)) -> 0 | AC65: =IF($F66<AC$22,0,AVERAGE(OFFSET($I$16,,$F66-AC$22+3)*AC$23,OFFSET($I$16,0,$F66-AC$22+2)*AC$23)) -> 0 | AD65: =IF($F66<AD$22,0,AVERAGE(OFFSET($I$16,,$F66-AD$22+3)*AD$23,OFFSET($I$16,0,$F66-AD$22+2)*AD$23)) -> 0 | ... AO65: =IF($F66<AO$22,0,AVERAGE(OFFSET($I$16,,$F66-AO$22+3)*AO$23,OFFSET($I$16,0,$F66-AO$22+2)*AO$23)) -> 0 | AP65: =SUM(L65:AI65) -> 0
J66: Total | L66: =SUM(L27:L65) -> 825000 | M66: =SUM(M27:M65) -> 825000 | N66: =SUM(N27:N65) -> 825000 | O66: =SUM(O27:O65) -> 825000 | P66: =SUM(P27:P65) -> 825000 | Q66: =SUM(Q27:Q65) -> 825000 | R66: =SUM(R27:R65) -> 825000 | S66: =SUM(S27:S65) -> 425683 | ... U66: =SUM(U27:U65) -> 0
F69: Proved Undeveloped Reserves - Production Schedule
B71: 1. | C71: Net Production
G73: Total Mmcfe | L73: =AP27 -> 51562.5 | M73: =AP28 -> 136125 | N73: =AP29 -> 196845 | O73: =AP30 -> 248681.4 | P73: =AP31 -> 294502.56 | Q73: =AP32 -> 335741.6 | R73: =AP33 -> 373052.09 | S73: =AP34 -> 382225.07 | T73: =AP35 -> 346253.31 | U73: =AP36 -> 302737.15 | V73: =AP37 -> 274195.67 | W73: =AP38 -> 251755.51 | X73: =AP39 -> 233312.69 | Y73: =AP40 -> 217877.63 | Z73: =AP41 -> 204930.22 | AA73: =AP42 -> 193953.2 | AB73: =AP43 -> 184420 | AC73: =AP44 -> 175894.66 | AD73: =AP45 -> 168075.99 | AE73: =AP46 -> 160842.12 | AF73: =AP47 -> 154156.03 | AG73: =AP48 -> 147926.54 | AH73: =AP49 -> 142009.48 | AI73: =AP50 -> 136329.1 | AJ73: =AP51 -> 130875.94 | AK73: =AP52 -> 125640.9 | AL73: =AP53 -> 120615.26 | AM73: =AP54 -> 114966.13 | AN73: =AP55 -> 103197.49 | AO73: =AP56 -> 86378.66 | AP73: =AP57 -> 70232.579 | AQ73: =AP58 -> 54732.342 | AR73: =AP59 -> 39852.114 | AS73: =AP60 -> 25567.095 | AT73: =AP61 -> 12252.564 | AU73: =AP62 -> 2967.3883
G74: Gas Mmcf | L74: =L73*'Inputs & Assumptions'!$L$58 -> 35320.312 | M74: =M73*'Inputs & Assumptions'!$L$58 -> 93245.625 | N74: =N73*'Inputs & Assumptions'!$L$58 -> 134838.82 | O74: =O73*'Inputs & Assumptions'!$L$58 -> 170346.76 | P74: =P73*'Inputs & Assumptions'!$L$58 -> 201734.25 | Q74: =Q73*'Inputs & Assumptions'!$L$58 -> 229983 | R74: =R73*'Inputs & Assumptions'!$L$58 -> 255540.68 | S74: =S73*'Inputs & Assumptions'!$L$58 -> 261824.18 | ... AU74: =AU73*'Inputs & Assumptions'!$L$58 -> 2032.661
G75: NGL MBbl | L75: =L73*'Inputs & Assumptions'!$L$59/'Inputs & Assumptions'!$L$35 -> 2566.0937 | M75: =M73*'Inputs & Assumptions'!$L$59/'Inputs & Assumptions'!$L$35 -> 6774.4875 | N75: =N73*'Inputs & Assumptions'!$L$59/'Inputs & Assumptions'!$L$35 -> 9796.3195 | O75: =O73*'Inputs & Assumptions'!$L$59/'Inputs & Assumptions'!$L$35 -> 12376.044 | P75: =P73*'Inputs & Assumptions'!$L$59/'Inputs & Assumptions'!$L$35 -> 14656.411 | Q75: =Q73*'Inputs & Assumptions'!$L$59/'Inputs & Assumptions'!$L$35 -> 16708.74 | R75: =R73*'Inputs & Assumptions'!$L$59/'Inputs & Assumptions'!$L$35 -> 18565.559 | S75: =S73*'Inputs & Assumptions'!$L$59/'Inputs & Assumptions'!$L$35 -> 19022.068 | ... AU75: =AU73*'Inputs & Assumptions'!$L$59/'Inputs & Assumptions'!$L$35 -> 147.67703
G76: Oil MBbl | L76: =L73*'Inputs & Assumptions'!$L$60/'Inputs & Assumptions'!$L$35 -> 140.9375 | M76: =M73*'Inputs & Assumptions'!$L$60/'Inputs & Assumptions'!$L$35 -> 372.075 | N76: =N73*'Inputs & Assumptions'!$L$60/'Inputs & Assumptions'!$L$35 -> 538.043 | O76: =O73*'Inputs & Assumptions'!$L$60/'Inputs & Assumptions'!$L$35 -> 679.72916 | P76: =P73*'Inputs & Assumptions'!$L$60/'Inputs & Assumptions'!$L$35 -> 804.97366 | Q76: =Q73*'Inputs & Assumptions'!$L$60/'Inputs & Assumptions'!$L$35 -> 917.69372 | R76: =R73*'Inputs & Assumptions'!$L$60/'Inputs & Assumptions'!$L$35 -> 1019.6757 | S76: =S73*'Inputs & Assumptions'!$L$60/'Inputs & Assumptions'!$L$35 -> 1044.7485 | ... AU76: =AU73*'Inputs & Assumptions'!$L$60/'Inputs & Assumptions'!$L$35 -> 8.1108614
B78: 2. | C78: Revenue
C80: a. | D80: Natural Gas Revenue
G82: $ MM | L82: =L74*'Commodity Price Assumptions'!$O$10/1000 -> 123.62109 | M82: =M74*'Commodity Price Assumptions'!$O$10/1000 -> 326.35969 | N82: =N74*'Commodity Price Assumptions'!$O$10/1000 -> 471.93589 | O82: =O74*'Commodity Price Assumptions'!$O$10/1000 -> 596.21366 | P82: =P74*'Commodity Price Assumptions'!$O$10/1000 -> 706.06989 | Q82: =Q74*'Commodity Price Assumptions'!$O$10/1000 -> 804.9405 | R82: =R74*'Commodity Price Assumptions'!$O$10/1000 -> 894.39238 | S82: =S74*'Commodity Price Assumptions'!$O$10/1000 -> 916.38462 | ... AU82: =AU74*'Commodity Price Assumptions'!$O$10/1000 -> 7.1143135
C84: b. | D84: NGL Revenue
G86: $ MM | L86: =L75*'Commodity Price Assumptions'!$O$122/1000 -> 56.140783 | M86: =M75*'Commodity Price Assumptions'!$O$122/1000 -> 148.21167 | N86: =N75*'Commodity Price Assumptions'!$O$122/1000 -> 214.32305 | O86: =O75*'Commodity Price Assumptions'!$O$122/1000 -> 270.76206 | P86: =P75*'Commodity Price Assumptions'!$O$122/1000 -> 320.65172 | Q86: =Q75*'Commodity Price Assumptions'!$O$122/1000 -> 365.55242 | R86: =R75*'Commodity Price Assumptions'!$O$122/1000 -> 406.17574 | S86: =S75*'Commodity Price Assumptions'!$O$122/1000 -> 416.1632 | ... AU86: =AU75*'Commodity Price Assumptions'!$O$122/1000 -> 3.2308655
C88: c. | D88: Oil Revenue
G90: $ MM | L90: =L76*'Commodity Price Assumptions'!$O$23/1000 -> 9.1246884 | M90: =M76*'Commodity Price Assumptions'!$O$23/1000 -> 24.089177 | N90: =N76*'Commodity Price Assumptions'!$O$23/1000 -> 34.83441 | O90: =O76*'Commodity Price Assumptions'!$O$23/1000 -> 44.007569 | P90: =P76*'Commodity Price Assumptions'!$O$23/1000 -> 52.116249 | Q90: =Q76*'Commodity Price Assumptions'!$O$23/1000 -> 59.414061 | R90: =R76*'Commodity Price Assumptions'!$O$23/1000 -> 66.01666 | S90: =S76*'Commodity Price Assumptions'!$O$23/1000 -> 67.639946 | ... AU90: =AU76*'Commodity Price Assumptions'!$O$23/1000 -> 0.52511988
B93: 3. | C93: Expenses
C95: a. | D95: Production Taxes
E97: Per Unit Price | G97: $/Mcfe | L97: ='Inputs & Assumptions'!$L$73 -> 0.04 | M97: ='Inputs & Assumptions'!$L$73 -> 0.04 | N97: ='Inputs & Assumptions'!$L$73 -> 0.04 | O97: ='Inputs & Assumptions'!$L$73 -> 0.04 | P97: ='Inputs & Assumptions'!$L$73 -> 0.04 | Q97: ='Inputs & Assumptions'!$L$73 -> 0.04 | R97: ='Inputs & Assumptions'!$L$73 -> 0.04 | S97: ='Inputs & Assumptions'!$L$73 -> 0.04 | ... AU97: ='Inputs & Assumptions'!$L$73 -> 0.04
E99: Total | G99: $MM | L99: =L97*L73/1000 -> 2.0625 | M99: =M97*M73/1000 -> 5.445 | N99: =N97*N73/1000 -> 7.8738 | O99: =O97*O73/1000 -> 9.947256 | P99: =P97*P73/1000 -> 11.780102 | Q99: =Q97*Q73/1000 -> 13.429664 | R99: =R97*R73/1000 -> 14.922083 | S99: =S97*S73/1000 -> 15.289003 | ... AU99: =AU97*AU73/1000 -> 0.11869553
C101: b. | D101: Lease Operating Expense (LOE)
E103: Per Unit Price | G103: $/Mcfe | L103: ='Inputs & Assumptions'!$L$74 -> 0.14 | M103: ='Inputs & Assumptions'!$L$74 -> 0.14 | N103: ='Inputs & Assumptions'!$L$74 -> 0.14 | O103: ='Inputs & Assumptions'!$L$74 -> 0.14 | P103: ='Inputs & Assumptions'!$L$74 -> 0.14 | Q103: ='Inputs & Assumptions'!$L$74 -> 0.14 | R103: ='Inputs & Assumptions'!$L$74 -> 0.14 | S103: ='Inputs & Assumptions'!$L$74 -> 0.14 | ... AU103: ='Inputs & Assumptions'!$L$74 -> 0.14
E105: Total | G105: $MM | L105: =L103*L73/1000 -> 7.21875 | M105: =M103*M73/1000 -> 19.0575 | N105: =N103*N73/1000 -> 27.5583 | O105: =O103*O73/1000 -> 34.815396 | P105: =P103*P73/1000 -> 41.230358 | Q105: =Q103*Q73/1000 -> 47.003825 | R105: =R103*R73/1000 -> 52.227292 | S105: =S103*S73/1000 -> 53.51151 | ... AU105: =AU103*AU73/1000 -> 0.41543436
C107: c. | D107: Transport Expense
E109: Per Unit Price | G109: $/Mcfe | L109: ='Inputs & Assumptions'!$L$75 -> 1.642 | M109: ='Inputs & Assumptions'!$L$75 -> 1.642 | N109: ='Inputs & Assumptions'!$L$75 -> 1.642 | O109: ='Inputs & Assumptions'!$L$75 -> 1.642 | P109: ='Inputs & Assumptions'!$L$75 -> 1.642 | Q109: ='Inputs & Assumptions'!$L$75 -> 1.642 | R109: ='Inputs & Assumptions'!$L$75 -> 1.642 | S109: ='Inputs & Assumptions'!$L$75 -> 1.642 | ... AU109: ='Inputs & Assumptions'!$L$75 -> 1.642
E111: Total | G111: $MM | L111: =L109*L73/1000 -> 84.665625 | M111: =M109*M73/1000 -> 223.51725 | N111: =N109*N73/1000 -> 323.21949 | O111: =O109*O73/1000 -> 408.33486 | P111: =P109*P73/1000 -> 483.5732 | Q111: =Q109*Q73/1000 -> 551.28771 | R111: =R109*R73/1000 -> 612.55153 | S111: =S109*S73/1000 -> 627.61357 | ... AU111: =AU109*AU73/1000 -> 4.8724516
B114: 4. | C114: Cash Flows
E116: Cash Flow from Operations | L116: =SUM(L82:L90)-L111 -> 104.22094 | M116: =SUM(M82:M90)-M111 -> 275.14328 | N116: =SUM(N82:N90)-N111 -> 397.87386 | O116: =SUM(O82:O90)-O111 -> 502.64842 | P116: =SUM(P82:P90)-P111 -> 595.26465 | Q116: =SUM(Q82:Q90)-Q111 -> 678.61926 | R116: =SUM(R82:R90)-R111 -> 754.03325 | S116: =SUM(S82:S90)-S111 -> 772.57419 | ... AU116: =SUM(AU82:AU90)-AU111 -> 5.9978473
E118: CapEx | L118: =L24 -> 563.75 | M118: =M24 -> 563.75 | N118: =N24 -> 563.75 | O118: =O24 -> 563.75 | P118: =P24 -> 563.75 | Q118: =Q24 -> 563.75 | R118: =R24 -> 563.75 | S118: =S24 -> 290.88338 | ... AU118: =AU24 -> 0
E120: FCF | L120: =L116-L118 -> -459.52906 | M120: =M116-M118 -> -288.60672 | N120: =N116-N118 -> -165.87614 | O120: =O116-O118 -> -61.101576 | P120: =P116-P118 -> 31.514655 | Q120: =Q116-Q118 -> 114.86926 | R120: =R116-R118 -> 190.28325 | S120: =S116-S118 -> 481.69081 | ... AU120: =AU116-AU118 -> 5.9978473
B122: 5. | C122: Discounted Cash Flow
E124: Year | L124: 1 | M124: 2 | N124: 3 | O124: 4 | P124: 5 | Q124: 6 | R124: 7 | S124: 8 | T124: 9 | U124: 10 | V124: 11 | W124: 12 | X124: 13 | Y124: 14 | Z124: 15 | AA124: 16 | AB124: 17 | AC124: 18 | AD124: 19 | AE124: 20 | AF124: 21 | AG124: 22 | AH124: 23 | AI124: 24 | AJ124: 25 | AK124: 26 | AL124: 27 | AM124: 28 | AN124: 29 | AO124: 30 | AP124: 31 | AQ124: 32 | AR124: 33 | AS124: 34 | AT124: 35 | AU124: 36
E126: Discount Factor | L126: =1/((1+'Inputs & Assumptions'!$L$40)^(L124-1)) -> 1 | M126: =1/((1+'Inputs & Assumptions'!$L$40)^(M124-1)) -> 0.92253222 | N126: =1/((1+'Inputs & Assumptions'!$L$40)^(N124-1)) -> 0.85106569 | O126: =1/((1+'Inputs & Assumptions'!$L$40)^(O124-1)) -> 0.78513552 | P126: =1/((1+'Inputs & Assumptions'!$L$40)^(P124-1)) -> 0.72431282 | Q126: =1/((1+'Inputs & Assumptions'!$L$40)^(Q124-1)) -> 0.66820191 | R126: =1/((1+'Inputs & Assumptions'!$L$40)^(R124-1)) -> 0.61643779 | S126: =1/((1+'Inputs & Assumptions'!$L$40)^(S124-1)) -> 0.56868372 | ... AU126: =1/((1+'Inputs & Assumptions'!$L$40)^(AU124-1)) -> 0.059477675
E128: DCF | G128: $MM | L128: =L120*L126 -> -459.52906 | M128: =M120*M126 -> -266.249 | N128: =N120*N126 -> -141.17149 | O128: =O120*O126 -> -47.973018 | P128: =P120*P126 -> 22.826468 | Q128: =Q120*Q126 -> 76.75586 | R128: =R120*R126 -> 117.29778 | S128: =S120*S126 -> 273.92972 | ... AU128: =AU120*AU126 -> 0.35673801
E130: PV | L130: =SUM(L128:AO128) -> 1999.4049

Sheet NAV
D2: =Cover!C5 -> Net Asset Value Model - Range Resources Corp. (NYSE:RRC)
D3: PUD Reserves
D5: Currently Running Commodity Price case: | H5: {=_xlfn.IFS('Inputs & Assumptions'!L37= 1,"Street", 'Inputs & Assumptions'!L37=2,"Bear",'Inputs & Assumptions'!L37=3,"Base",'Inputs & Assumptions'!L37=4,"Bull")} -> Street
B9: 1. | C9: NAV Calculation | T9: First year production % EUR | V9: EUR
U10: =N36 -> 0.24943221 | V10: 13500 | W10: 14000 | X10: 14500 | Y10: 15000 | Z10: 15500 | AA10: 16000 | AB10: 16500
C11: a. | D11: Pre-tax Asset Value | L11: units | U11: 0.11 | V11: 0.16870335 | W11: 0.17959094 | X11: 0.19047852 | Y11: 0.2013661 | Z11: 0.21225368 | AA11: 0.22314126 | AB11: 0.23402884
U12: 0.115 | V12: 0.18218114 | W12: 0.19356523 | X12: 0.20494932 | Y12: 0.2163334 | Z12: 0.22771749 | AA12: 0.23910157 | AB12: 0.25048566
H13: Proved Developed Reserves | L13: $MM | N13: ='PD Reserves'!L81 -> 17113.522 | U13: 0.12 | V13: 0.19689265 | W13: 0.20879213 | X13: 0.22069161 | Y13: 0.23259109 | Z13: 0.24449058 | AA13: 0.25639006 | AB13: 0.26828954
H14: Proved Undeveloped Assets | L14: $MM | N14: ='PUD Reserves'!L130 -> 1999.4049 | U14: 0.125 | V14: 0.21218643 | W14: 0.22460169 | X14: 0.23701695 | Y14: 0.24943221 | Z14: 0.26184747 | AA14: 0.27426273 | AB14: 0.28667799 | AU14: 15000
H15: Pre-tax Asset Value | L15: $MM | N15: =SUM(N13:N14) -> 19112.927 | U15: 0.13 | V15: 0.22623514 | W15: 0.23911563 | X15: 0.25199613 | Y15: 0.26487662 | Z15: 0.27775712 | AA15: 0.29063761 | AB15: 0.30351811 | AU15: 0.125
U16: 0.135 | V16: 0.23876131 | W16: 0.25205334 | X16: 0.26534537 | Y16: 0.2786374 | Z16: 0.29192943 | AA16: 0.30522146 | AB16: 0.31851349
U17: 0.14 | V17: 0.24996415 | W17: 0.26362128 | X17: 0.2772784 | Y17: 0.29093553 | Z17: 0.30459265 | AA17: 0.31824978 | AB17: 0.3319069
C18: b. | D18: After-Tax Asset Value | L18: units
H20: PV of G&A | L20: $MM | N20: =SUM(DCF!K55:AT55) -> -2757.1566 | V20: Bear / Base / Bull
H21: PV of Tax Expenses | L21: $MM | N21: =SUM(DCF!K54:AT54) -> -3255.3603 | T21: Effective Tax Rate | U21: =N36 -> 0.24943221 | V21: 2 | W21: 3 | X21: 4
H22: After tax Asset Value | L22: $MM | N22: =N15+N20+N21 -> 13100.41 | U22: 0.25 | V22: -0.20166643 | W22: 0.24943221 | X22: 0.41374535
U23: 0.24 | V23: -0.19403791 | W23: 0.26308881 | X23: 0.4295964
C24: c. | D24: Total Asset Value | L24: units | U24: 0.23 | V24: -0.1864094 | W24: 0.27674541 | X24: 0.44544746
U25: 0.22 | V25: -0.17878088 | W25: 0.29040201 | X25: 0.46129851
H26: Cash & Investments | L26: $MM | N26: 304.49 | U26: 0.21 | V26: -0.17115237 | W26: 0.30405861 | X26: 0.47714956
H27: Net operating Losses | L27: $MM | N27: 341.45111 | U27: 0.2 | V27: -0.16352385 | W27: 0.31771521 | X27: 0.49300062
H28: Net Debt | L28: $MM | N28: -1694.762 | AU28: 1
H29: Asset Retirement Obligations | L29: $MM | N29: -138.37 | AU29: 0.25
H30: Net Asset Value | L30: $MM | N30: =SUM(N22:N29) -> 11913.22 | V30: long term Natural Gas price
T31: WACC | U31: =N36 -> 0.24943221 | V31: =W31-0.2 -> 3.24 | W31: =X31-0.2 -> 3.44 | X31: =Y31-0.2 -> 3.64 | Y31: 3.84 | Z31: =Y31+0.2 -> 4.04 | AA31: =Z31+0.2 -> 4.24 | AB31: =AA31+0.2 -> 4.44
C32: d. | D32: Net Asset Value | L32: units | U32: =U33-0.005 -> 0.069 | V32: 0.29410367 | W32: 0.33500206 | X32: 0.37590045 | Y32: 0.41679884 | Z32: 0.45769723 | AA32: 0.49859563 | AB32: 0.53949402
U33: =U34-0.005 -> 0.074 | V33: 0.24028061 | W33: 0.27922347 | X33: 0.31816633 | Y33: 0.3571092 | Z33: 0.39605206 | AA33: 0.43499492 | AB33: 0.47393779
H34: Diluted Shares Outstanding | L34: MM shares | N34: ='Inputs & Assumptions'!L25 -> 239.03 | U34: =U35-0.005 -> 0.079 | V34: 0.18998788 | W34: 0.22710444 | X34: 0.264221 | Y34: 0.30133757 | Z34: 0.33845413 | AA34: 0.37557069 | AB34: 0.41268725
H35: Net Asset Value | L35: $ | N35: =N30/N34 -> 49.839851 | U35: 0.084 | V35: 0.14293283 | W35: 0.17834168 | X35: 0.21375053 | Y35: 0.24915938 | Z35: 0.28456823 | AA35: 0.31997708 | AB35: 0.35538594
H36: Implied Upside | L36: % | N36: =(N35-'Inputs & Assumptions'!L24)/'Inputs & Assumptions'!L24 -> 0.24943221 | U36: =U35+0.005 -> 0.089 | V36: 0.098850906 | W36: 0.13266102 | X36: 0.16647113 | Y36: 0.20028124 | Z36: 0.23409135 | AA36: 0.26790147 | AB36: 0.30171158
U37: =U36+0.005 -> 0.094 | V37: 0.057502696 | W37: 0.089814328 | X37: 0.12212596 | Y37: 0.15443759 | Z37: 0.18674922 | AA37: 0.21906086 | AB37: 0.25137249
U38: =U37+0.005 -> 0.099 | V38: 0.018671252 | W38: 0.049576765 | X38: 0.080482278 | Y38: 0.11138779 | Z38: 0.1422933 | AA38: 0.17319882 | AB38: 0.20410433
AU39: =3.84 -> 3.84
AU40: 0.083972982
V41: Natural Gas Liquids Price
U42: =N36 -> 0.24943221 | V42: -0.06 | W42: -0.04 | X42: -0.02 | Y42: 0 | Z42: 0.02 | AA42: 0.04 | AB42: 0.06
T43: WACC | U43: =U44-0.005 -> 0.069 | V43: 0.35070191 | W43: 0.37273422 | X43: 0.39476653 | Y43: 0.41679884 | Z43: 0.43883116 | AA43: 0.46086347 | AB43: 0.48289578
U44: =U45-0.005 -> 0.074 | V44: 0.29322656 | W44: 0.31452077 | X44: 0.33581498 | Y44: 0.3571092 | Z44: 0.37840341 | AA44: 0.39969762 | AB44: 0.42099184
U45: =U46-0.005 -> 0.079 | V45: 0.23953091 | W45: 0.26013313 | X45: 0.28073535 | Y45: 0.30133757 | Z45: 0.32193978 | AA45: 0.342542 | AB45: 0.36314422
U46: 0.084 | V46: 0.18930161 | W46: 0.2092542 | X46: 0.22920679 | Y46: 0.24915938 | Z46: 0.26911197 | AA46: 0.28906456 | AB46: 0.30901715
U47: =U46+0.005 -> 0.089 | V47: 0.14225542 | W47: 0.16159736 | X47: 0.1809393 | Y47: 0.20028124 | Z47: 0.21962318 | AA47: 0.23896512 | AB47: 0.25830706
U48: =U47+0.005 -> 0.094 | V48: 0.098135993 | W48: 0.11690319 | X48: 0.13567039 | Y48: 0.15443759 | Z48: 0.17320479 | AA48: 0.19197199 | AB48: 0.21073919
U49: =U48+0.005 -> 0.099 | V49: 0.05671102 | W49: 0.07493661 | X49: 0.093162201 | Y49: 0.11138779 | Z49: 0.12961338 | AA49: 0.14783897 | AB49: 0.16606456 | AU49: 0

Sheet DCF
D2: =Cover!C5 -> Net Asset Value Model - Range Resources Corp. (NYSE:RRC)
D3: PUD Reserves
D5: Currently Running Commodity Price case: | H5: {=_xlfn.IFS('Inputs & Assumptions'!L37= 1,"Street", 'Inputs & Assumptions'!L37=2,"Bear",'Inputs & Assumptions'!L37=3,"Base",'Inputs & Assumptions'!L37=4,"Bull")} -> Street
K6: FY 2025 | L6: FY 2026 | M6: FY 2027 | N6: FY 2028 | O6: FY 2029 | P6: FY 2030 | Q6: FY 2031 | R6: FY 2032 | S6: FY 2033 | T6: FY 2034 | U6: FY 2035 | V6: FY 2036 | W6: FY 2037 | X6: FY 2038 | Y6: FY 2039 | Z6: FY 2040 | AA6: FY 2041 | AB6: FY 2042 | AC6: FY 2043 | AD6: FY 2044 | AE6: FY 2045 | AF6: FY 2046 | AG6: FY 2047 | AH6: FY 2048 | AI6: FY 2049 | AJ6: FY 2050 | AK6: FY 2051 | AL6: FY 2052 | AM6: FY 2053 | AN6: FY 2054 | AO6: FY 2055 | AP6: FY 2056 | AQ6: FY 2057 | AR6: FY 2058 | AS6: FY 2059 | AT6: FY 2060 | AU6: FY 2061
F8: Period | K8: 1 | L8: 2 | M8: 3 | N8: 4 | O8: 5 | P8: 6 | Q8: 7 | R8: 8 | S8: 9 | T8: 10 | U8: 11 | V8: 12 | W8: 13 | X8: 14 | Y8: 15 | Z8: 16 | AA8: 17 | AB8: 18 | AC8: 19 | AD8: 20 | AE8: 21 | AF8: 22 | AG8: 23 | AH8: 24 | AI8: 25 | AJ8: 26 | AK8: 27 | AL8: 28 | AM8: 29 | AN8: 30 | AO8: 31 | AP8: 32 | AQ8: 33 | AR8: 34 | AS8: 35 | AT8: 36 | AU8: 37
B10: 1. | C10: Commodity Price Assumptions | I10: units
F12: Natural Gas | I12: $ / Mcf | K12: ='Commodity Price Assumptions'!O10 -> 3.5 | L12: ='Commodity Price Assumptions'!P10 -> 3.84 | M12: ='Commodity Price Assumptions'!Q10 -> 3.85 | N12: ='Commodity Price Assumptions'!R10 -> 3.81 | O12: ='Commodity Price Assumptions'!$S$10 -> 3.84 | P12: ='Commodity Price Assumptions'!$S$10 -> 3.84 | Q12: ='Commodity Price Assumptions'!$S$10 -> 3.84 | R12: ='Commodity Price Assumptions'!$S$10 -> 3.84 | S12: ='Commodity Price Assumptions'!$S$10 -> 3.84 | T12: ='Commodity Price Assumptions'!$S$10 -> 3.84 | U12: ='Commodity Price Assumptions'!$S$10 -> 3.84 | V12: ='Commodity Price Assumptions'!$S$10 -> 3.84 | ... AU12: ='Commodity Price Assumptions'!$S$10 -> 3.84
F13: NGL | I13: $ / Bbl | K13: ='Commodity Price Assumptions'!O122 -> 21.877916 | L13: ='Commodity Price Assumptions'!P122 -> 21.265247 | M13: ='Commodity Price Assumptions'!Q122 -> 22.148911 | N13: ='Commodity Price Assumptions'!R122 -> 21.493231 | O13: ='Commodity Price Assumptions'!$S$122 -> 21.052987 | P13: ='Commodity Price Assumptions'!$S$122 -> 21.052987 | Q13: ='Commodity Price Assumptions'!$S$122 -> 21.052987 | R13: ='Commodity Price Assumptions'!$S$122 -> 21.052987 | S13: ='Commodity Price Assumptions'!$S$122 -> 21.052987 | T13: ='Commodity Price Assumptions'!$S$122 -> 21.052987 | U13: ='Commodity Price Assumptions'!$S$122 -> 21.052987 | V13: ='Commodity Price Assumptions'!$S$122 -> 21.052987 | ... AU13: ='Commodity Price Assumptions'!$S$122 -> 21.052987
F14: Oil | I14: $ / Bbl | K14: ='Commodity Price Assumptions'!O23 -> 64.7428 | L14: ='Commodity Price Assumptions'!P23 -> 58.7556 | M14: ='Commodity Price Assumptions'!Q23 -> 63.66 | N14: ='Commodity Price Assumptions'!R23 -> 67.5392 | O14: ='Commodity Price Assumptions'!$S$23 -> 69.1789 | P14: ='Commodity Price Assumptions'!$S$23 -> 69.1789 | Q14: ='Commodity Price Assumptions'!$S$23 -> 69.1789 | R14: ='Commodity Price Assumptions'!$S$23 -> 69.1789 | S14: ='Commodity Price Assumptions'!$S$23 -> 69.1789 | T14: ='Commodity Price Assumptions'!$S$23 -> 69.1789 | U14: ='Commodity Price Assumptions'!$S$23 -> 69.1789 | V14: ='Commodity Price Assumptions'!$S$23 -> 69.1789 | ... AU14: ='Commodity Price Assumptions'!$S$23 -> 69.1789
B16: 2. | C16: Production | I16: units
F18: Natural Gas | I18: Mmcf | K18: ='PD Reserves'!L25+'PUD Reserves'!L74 -> 564475.72 | L18: ='PD Reserves'!M25+'PUD Reserves'!M74 -> 595943.26 | M18: ='PD Reserves'!N25+'PUD Reserves'!N74 -> 612401.58 | N18: ='PD Reserves'!O25+'PUD Reserves'!O74 -> 625274.35 | O18: ='PD Reserves'!P25+'PUD Reserves'!P74 -> 632734.64 | P18: ='PD Reserves'!Q25+'PUD Reserves'!Q74 -> 639433.37 | Q18: ='PD Reserves'!R25+'PUD Reserves'!R74 -> 644518.53 | R18: ='PD Reserves'!S25+'PUD Reserves'!S74 -> 632365.54 | ... AU18: ='PD Reserves'!AV25+'PUD Reserves'!AV74 -> 0
F19: NGL | I19: MBbl | K19: ='PD Reserves'!L26+'PUD Reserves'!L75 -> 41010.329 | L19: ='PD Reserves'!M26+'PUD Reserves'!M75 -> 43296.511 | M19: ='PD Reserves'!N26+'PUD Reserves'!N75 -> 44492.242 | N19: ='PD Reserves'!O26+'PUD Reserves'!O75 -> 45427.475 | O19: ='PD Reserves'!P26+'PUD Reserves'!P75 -> 45969.48 | P19: ='PD Reserves'!Q26+'PUD Reserves'!Q75 -> 46456.157 | Q19: ='PD Reserves'!R26+'PUD Reserves'!R75 -> 46825.604 | R19: ='PD Reserves'!S26+'PUD Reserves'!S75 -> 45942.664 | ... AU19: ='PD Reserves'!AV26+'PUD Reserves'!AV75 -> 0
F20: Oil | I20: MBbl | K20: ='PD Reserves'!L27+'PUD Reserves'!L76 -> 2252.4092 | L20: ='PD Reserves'!M27+'PUD Reserves'!M76 -> 2377.9731 | M20: ='PD Reserves'!N27+'PUD Reserves'!N76 -> 2443.6462 | N20: ='PD Reserves'!O27+'PUD Reserves'!O76 -> 2495.012 | O20: ='PD Reserves'!P27+'PUD Reserves'!P76 -> 2524.7806 | P20: ='PD Reserves'!Q27+'PUD Reserves'!Q76 -> 2551.5103 | Q20: ='PD Reserves'!R27+'PUD Reserves'!R76 -> 2571.8014 | R20: ='PD Reserves'!S27+'PUD Reserves'!S76 -> 2523.3078 | ... AU20: ='PD Reserves'!AV27+'PUD Reserves'!AV76 -> 0
F21: Annual Pruduction | I21: Mmcfe | K21: ='PD Reserves'!L24+'PUD Reserves'!L73 -> 824052.15 | L21: ='PD Reserves'!M24+'PUD Reserves'!M73 -> 869990.17 | M21: ='PD Reserves'!N24+'PUD Reserves'!N73 -> 894016.91 | N21: ='PD Reserves'!O24+'PUD Reserves'!O73 -> 912809.27 | O21: ='PD Reserves'!P24+'PUD Reserves'!P73 -> 923700.21 | P21: ='PD Reserves'!Q24+'PUD Reserves'!Q73 -> 933479.37 | Q21: ='PD Reserves'!R24+'PUD Reserves'!R73 -> 940902.96 | R21: ='PD Reserves'!S24+'PUD Reserves'!S73 -> 923161.38 | ... AU21: ='PD Reserves'!AV24+'PUD Reserves'!AV73 -> 0
F22: Daily Production | I22: Mmcfe / d | K22: =IFERROR(K21/365,"N/A") -> 2257.6771 | L22: =IFERROR(L21/365,"N/A") -> 2383.5347 | M22: =IFERROR(M21/365,"N/A") -> 2449.3614 | N22: =IFERROR(N21/365,"N/A") -> 2500.8473 | O22: =IFERROR(O21/365,"N/A") -> 2530.6855 | P22: =IFERROR(P21/365,"N/A") -> 2557.4777 | Q22: =IFERROR(Q21/365,"N/A") -> 2577.8163 | R22: =IFERROR(R21/365,"N/A") -> 2529.2093 | ... AU22: =IFERROR(AU21/365,"N/A") -> 0
F24: PD Annual Production: | I24: Mmcfe | K24: ='PD Reserves'!L24 -> 772489.65 | L24: ='PD Reserves'!M24 -> 733865.17 | M24: ='PD Reserves'!N24 -> 697171.91 | N24: ='PD Reserves'!O24 -> 664127.87 | O24: ='PD Reserves'!P24 -> 629197.65 | P24: ='PD Reserves'!Q24 -> 597737.77 | Q24: ='PD Reserves'!R24 -> 567850.88 | R24: ='PD Reserves'!S24 -> 540936.3 | ... AU24: ='PD Reserves'!AV24 -> 0 | AW24: =SUM(K24:AU24) -> 11930793
F25: PUD Annual Production: | I25: Mmcfe | K25: ='PUD Reserves'!L73 -> 51562.5 | L25: ='PUD Reserves'!M73 -> 136125 | M25: ='PUD Reserves'!N73 -> 196845 | N25: ='PUD Reserves'!O73 -> 248681.4 | O25: ='PUD Reserves'!P73 -> 294502.56 | P25: ='PUD Reserves'!Q73 -> 335741.6 | Q25: ='PUD Reserves'!R73 -> 373052.09 | R25: ='PUD Reserves'!S73 -> 382225.07 | ... AU25: ='PUD Reserves'!AV73 -> 0
B28: 3. | C28: Revenue | I28: units
F30: Natural Gas | I30: $MM | K30: ='PD Reserves'!L33+'PUD Reserves'!L82 -> 1975.665 | L30: ='PD Reserves'!M33+'PUD Reserves'!M82 -> 2256.7186 | M30: ='PD Reserves'!N33+'PUD Reserves'!N82 -> 2310.5525 | N30: ='PD Reserves'!O33+'PUD Reserves'!O82 -> 2329.4878 | O30: ='PD Reserves'!P33+'PUD Reserves'!P82 -> 2361.1114 | P30: ='PD Reserves'!Q33+'PUD Reserves'!Q82 -> 2377.2299 | Q30: ='PD Reserves'!R33+'PUD Reserves'!R82 -> 2388.0673 | R30: ='PD Reserves'!S33+'PUD Reserves'!S82 -> 2339.2635 | ... AU30: ='PD Reserves'!AV33+'PUD Reserves'!AV82 -> 0
F31: NGL | I31: $MM | K31: ='PD Reserves'!L37+'PUD Reserves'!L86 -> 1427.1008 | L31: ='PD Reserves'!M37+'PUD Reserves'!M86 -> 1414.1509 | M31: ='PD Reserves'!N37+'PUD Reserves'!N86 -> 1466.9404 | N31: ='PD Reserves'!O37+'PUD Reserves'!O86 -> 1428.6847 | O31: ='PD Reserves'!P37+'PUD Reserves'!P86 -> 1395.2026 | P31: ='PD Reserves'!Q37+'PUD Reserves'!Q86 -> 1386.3757 | Q31: ='PD Reserves'!R37+'PUD Reserves'!R86 -> 1375.9579 | R31: ='PD Reserves'!S37+'PUD Reserves'!S86 -> 1339.9803 | ... AU31: ='PD Reserves'!AV37+'PUD Reserves'!AV86 -> 0
F32: Oil | I32: $MM | K32: ='PD Reserves'!L41+'PUD Reserves'!L90 -> 145.82728 | L32: ='PD Reserves'!M41+'PUD Reserves'!M90 -> 141.94693 | M32: ='PD Reserves'!N41+'PUD Reserves'!N90 -> 156.14511 | N32: ='PD Reserves'!O41+'PUD Reserves'!O90 -> 166.61032 | O32: ='PD Reserves'!P41+'PUD Reserves'!P90 -> 171.0906 | P32: ='PD Reserves'!Q41+'PUD Reserves'!Q90 -> 172.43969 | Q32: ='PD Reserves'!R41+'PUD Reserves'!R90 -> 173.39101 | R32: ='PD Reserves'!S41+'PUD Reserves'!S90 -> 169.92505 | ... AU32: ='PD Reserves'!AV41+'PUD Reserves'!AV90 -> 0
F33: Revenue | I33: $MM | K33: =SUM(K30:K32) -> 3548.5931 | L33: =SUM(L30:L32) -> 3812.8165 | M33: =SUM(M30:M32) -> 3933.638 | N33: =SUM(N30:N32) -> 3924.7828 | O33: =SUM(O30:O32) -> 3927.4046 | P33: =SUM(P30:P32) -> 3936.0453 | Q33: =SUM(Q30:Q32) -> 3937.4162 | R33: =SUM(R30:R32) -> 3849.1688 | ... AU33: =SUM(AU30:AU32) -> 0
B35: 3. | C35: Expenses | I35: units
F37: Production Taxes | I37: $MM | K37: ='PD Reserves'!L50+'PUD Reserves'!L99 -> 32.962086 | L37: ='PD Reserves'!M50+'PUD Reserves'!M99 -> 34.799607 | M37: ='PD Reserves'!N50+'PUD Reserves'!N99 -> 35.760676 | N37: ='PD Reserves'!O50+'PUD Reserves'!O99 -> 36.512371 | O37: ='PD Reserves'!P50+'PUD Reserves'!P99 -> 36.948008 | P37: ='PD Reserves'!Q50+'PUD Reserves'!Q99 -> 37.339175 | Q37: ='PD Reserves'!R50+'PUD Reserves'!R99 -> 37.636119 | R37: ='PD Reserves'!S50+'PUD Reserves'!S99 -> 36.926455 | ... AU37: ='PD Reserves'!AV50+'PUD Reserves'!AV99 -> 0
F38: LOE | I38: $MM | K38: ='PD Reserves'!L56+'PUD Reserves'!L105 -> 115.3673 | L38: ='PD Reserves'!M56+'PUD Reserves'!M105 -> 121.79862 | M38: ='PD Reserves'!N56+'PUD Reserves'!N105 -> 125.16237 | N38: ='PD Reserves'!O56+'PUD Reserves'!O105 -> 127.7933 | O38: ='PD Reserves'!P56+'PUD Reserves'!P105 -> 129.31803 | P38: ='PD Reserves'!Q56+'PUD Reserves'!Q105 -> 130.68711 | Q38: ='PD Reserves'!R56+'PUD Reserves'!R105 -> 131.72641 | R38: ='PD Reserves'!S56+'PUD Reserves'!S105 -> 129.24259 | ... AU38: ='PD Reserves'!AV56+'PUD Reserves'!AV105 -> 0
F39: Transportation | I39: $MM | K39: ='PD Reserves'!L62+'PUD Reserves'!L111 -> 1353.0936 | L39: ='PD Reserves'!M62+'PUD Reserves'!M111 -> 1428.5239 | M39: ='PD Reserves'!N62+'PUD Reserves'!N111 -> 1467.9758 | N39: ='PD Reserves'!O62+'PUD Reserves'!O111 -> 1498.8328 | O39: ='PD Reserves'!P62+'PUD Reserves'!P111 -> 1516.7157 | P39: ='PD Reserves'!Q62+'PUD Reserves'!Q111 -> 1532.7731 | Q39: ='PD Reserves'!R62+'PUD Reserves'!R111 -> 1544.9627 | R39: ='PD Reserves'!S62+'PUD Reserves'!S111 -> 1515.831 | ... AU39: ='PD Reserves'!AV62+'PUD Reserves'!AV111 -> 0
F40: G&A | I40: $MM | K40: =K33*'Inputs & Assumptions'!$L$98 -> 262.59589 | L40: =L33*'Inputs & Assumptions'!$L$98 -> 282.14842 | M40: =M33*'Inputs & Assumptions'!$L$98 -> 291.08921 | N40: =N33*'Inputs & Assumptions'!$L$98 -> 290.43393 | O40: =O33*'Inputs & Assumptions'!$L$98 -> 290.62794 | P40: =P33*'Inputs & Assumptions'!$L$98 -> 291.26736 | Q40: =Q33*'Inputs & Assumptions'!$L$98 -> 291.3688 | R40: =R33*'Inputs & Assumptions'!$L$98 -> 284.83849 | ... AU40: =AU33*'Inputs & Assumptions'!$L$98 -> 0
F41: TOTAL Expenses | I41: $MM | K41: =SUM(K37:K40) -> 1764.0189 | L41: =SUM(L37:L40) -> 1867.2705 | M41: =SUM(M37:M40) -> 1919.988 | N41: =SUM(N37:N40) -> 1953.5724 | O41: =SUM(O37:O40) -> 1973.6097 | P41: =SUM(P37:P40) -> 1992.0668 | Q41: =SUM(Q37:Q40) -> 2005.694 | R41: =SUM(R37:R40) -> 1966.8385 | ... AU41: =SUM(AU37:AU40) -> 0
B43: 5. | C43: Taxable Income | I43: units
F45: EBITDA | I45: $MM | K45: =K33-K41 -> 1784.5742 | L45: =L33-L41 -> 1945.546 | M45: =M33-M41 -> 2013.65 | N45: =N33-N41 -> 1971.2104 | O45: =O33-O41 -> 1953.7948 | P45: =P33-P41 -> 1943.9786 | Q45: =Q33-Q41 -> 1931.7222 | R45: =R33-R41 -> 1882.3303 | ... AT45: =AT33-AT41 -> 4.6593153
F46: PD Reserves - DD&A | I46: $MM | K46: =-K24/$AW$24*'Inputs & Assumptions'!$L$80 -> -415.95123 | L46: =-L24/$AW$24*'Inputs & Assumptions'!$L$80 -> -395.15367 | M46: =-M24/$AW$24*'Inputs & Assumptions'!$L$80 -> -375.39598 | N46: =-N24/$AW$24*'Inputs & Assumptions'!$L$80 -> -357.60324 | O46: =-O24/$AW$24*'Inputs & Assumptions'!$L$80 -> -338.79488 | P46: =-P24/$AW$24*'Inputs & Assumptions'!$L$80 -> -321.85513 | Q46: =-Q24/$AW$24*'Inputs & Assumptions'!$L$80 -> -305.76238 | R46: =-R24/$AW$24*'Inputs & Assumptions'!$L$80 -> -291.27008 | ... AT46: =-AT24/$AW$24*'Inputs & Assumptions'!$L$80 -> 0
F47: Maintainance CapEx | I47: $MM | K47: =-'PD Reserves'!L69 -> -54.868804 | L47: =-'PD Reserves'!M69 -> -52.125363 | M47: =-'PD Reserves'!N69 -> -49.519095 | N47: =-'PD Reserves'!O69 -> -47.172026 | O47: =-'PD Reserves'!P69 -> -44.690983 | P47: =-'PD Reserves'!Q69 -> -42.456434 | Q47: =-'PD Reserves'!R69 -> -40.333613 | R47: =-'PD Reserves'!S69 -> -38.42191 | ... AT47: =-'PD Reserves'!AU69 -> 0
F48: PUD reserves - DD&A | I48: $MM | K48: =-K25/SUM($K$25:$AU$25)*'PUD Reserves'!$AP$24 -> -35.234375 | L48: =-L25/SUM($K$25:$AU$25)*'PUD Reserves'!$AP$24 -> -93.01875 | M48: =-M25/SUM($K$25:$AU$25)*'PUD Reserves'!$AP$24 -> -134.51075 | N48: =-N25/SUM($K$25:$AU$25)*'PUD Reserves'!$AP$24 -> -169.93229 | O48: =-O25/SUM($K$25:$AU$25)*'PUD Reserves'!$AP$24 -> -201.24342 | P48: =-P25/SUM($K$25:$AU$25)*'PUD Reserves'!$AP$24 -> -229.42343 | Q48: =-Q25/SUM($K$25:$AU$25)*'PUD Reserves'!$AP$24 -> -254.91893 | R48: =-R25/SUM($K$25:$AU$25)*'PUD Reserves'!$AP$24 -> -261.18713 | ... AT48: =-AT25/SUM($K$25:$AU$25)*'PUD Reserves'!$AP$24 -> -2.0277153
F49: Taxable Income | I49: $MM | K49: =SUM(K45:K48) -> 1278.5198 | L49: =SUM(L45:L48) -> 1405.2482 | M49: =SUM(M45:M48) -> 1454.2242 | N49: =SUM(N45:N48) -> 1396.5029 | O49: =SUM(O45:O48) -> 1369.0656 | P49: =SUM(P45:P48) -> 1350.2436 | Q49: =SUM(Q45:Q48) -> 1330.7073 | R49: =SUM(R45:R48) -> 1291.4512 | ... AT49: =SUM(AT45:AT48) -> 2.6315999
B51: Discount factor | K51: =1/((1+'Inputs & Assumptions'!$L$40)^(K8-1)) -> 1 | L51: =1/((1+'Inputs & Assumptions'!$L$40)^(L8-1)) -> 0.92253222 | M51: =1/((1+'Inputs & Assumptions'!$L$40)^(M8-1)) -> 0.85106569 | N51: =1/((1+'Inputs & Assumptions'!$L$40)^(N8-1)) -> 0.78513552 | O51: =1/((1+'Inputs & Assumptions'!$L$40)^(O8-1)) -> 0.72431282 | P51: =1/((1+'Inputs & Assumptions'!$L$40)^(P8-1)) -> 0.66820191 | Q51: =1/((1+'Inputs & Assumptions'!$L$40)^(Q8-1)) -> 0.61643779 | R51: =1/((1+'Inputs & Assumptions'!$L$40)^(R8-1)) -> 0.56868372 | ... AU51: =1/((1+'Inputs & Assumptions'!$L$40)^(AU8-1)) -> 0.054870071
B54: Income Tax Expense | I54: $MM | K54: =-K49*'Inputs & Assumptions'!$L$34*DCF!K51 -> -319.62994 | L54: =-L49*'Inputs & Assumptions'!$L$34*DCF!L51 -> -324.09668 | M54: =-M49*'Inputs & Assumptions'!$L$34*DCF!M51 -> -309.41008 | N54: =-N49*'Inputs & Assumptions'!$L$34*DCF!N51 -> -274.111 | O54: =-O49*'Inputs & Assumptions'!$L$34*DCF!O51 -> -247.90793 | P54: =-P49*'Inputs & Assumptions'!$L$34*DCF!P51 -> -225.55883 | Q54: =-Q49*'Inputs & Assumptions'!$L$34*DCF!Q51 -> -205.07457 | R54: =-R49*'Inputs & Assumptions'!$L$34*DCF!R51 -> -183.60682 | ... AU54: =-AU49*'Inputs & Assumptions'!$L$34*DCF!AU51 -> 0
B55: G&A | I55: $MM | K55: =-K51*K40 -> -262.59589 | L55: =-L51*L40 -> -260.29101 | M55: =-M51*M40 -> -247.73604 | N55: =-N51*N40 -> -228.03 | O55: =-O51*O40 -> -210.50554 | P55: =-P51*P40 -> -194.6254 | Q55: =-Q51*Q40 -> -179.61074 | R55: =-R51*R40 -> -161.98301 | ... AU55: =-AU51*AU40 -> 0
